<stg><name>relu<array<ap_fixed,10u>,array<ap_ufixed<8,2,5,3,0>,10u>,relu_config20></name>


<trans_list>

<trans id="72" from="1" to="2">
<condition id="-1">
<or_exp><and_exp></and_exp></or_exp>
</condition>
</trans>
</trans_list>



<state_list>

<state id="1" st_id="1">

<operation id="3" st_id="1" stage="1" lat="1">
<core>FIFO</core>
<MemPortIdVec></MemPortIdVec>
<condition id="-1">
<or_exp><and_exp></and_exp></or_exp>
</condition>

<Node id="44" bw="160" op_0_bw="160" op_1_bw="16" op_2_bw="16" op_3_bw="16" op_4_bw="16" op_5_bw="16" op_6_bw="16" op_7_bw="16" op_8_bw="16" op_9_bw="16" op_10_bw="16">
<![CDATA[
ReLUActLoop:23  %empty = call { i16, i16, i16, i16, i16, i16, i16, i16, i16, i16 } @_ssdm_op_Read.ap_fifo.volatile.i16P.i16P.i16P.i16P.i16P.i16P.i16P.i16P.i16P.i16P(i16* %data_V_data_0_V, i16* %data_V_data_1_V, i16* %data_V_data_2_V, i16* %data_V_data_3_V, i16* %data_V_data_4_V, i16* %data_V_data_5_V, i16* %data_V_data_6_V, i16* %data_V_data_7_V, i16* %data_V_data_8_V, i16* %data_V_data_9_V)

]]></Node>
<StgValue><ssdm name="empty"/></StgValue>
</operation>

<operation id="4" st_id="1" stage="1" lat="1">
<core>NULL</core>
<MemPortIdVec></MemPortIdVec>
<condition id="-1">
<or_exp><and_exp></and_exp></or_exp>
</condition>

<Node id="45" bw="16" op_0_bw="160">
<![CDATA[
ReLUActLoop:24  %tmp_data_V_8_0 = extractvalue { i16, i16, i16, i16, i16, i16, i16, i16, i16, i16 } %empty, 0

]]></Node>
<StgValue><ssdm name="tmp_data_V_8_0"/></StgValue>
</operation>

<operation id="5" st_id="1" stage="1" lat="1">
<core>NULL</core>
<MemPortIdVec></MemPortIdVec>
<condition id="-1">
<or_exp><and_exp></and_exp></or_exp>
</condition>

<Node id="46" bw="16" op_0_bw="160">
<![CDATA[
ReLUActLoop:25  %tmp_data_V_8_1 = extractvalue { i16, i16, i16, i16, i16, i16, i16, i16, i16, i16 } %empty, 1

]]></Node>
<StgValue><ssdm name="tmp_data_V_8_1"/></StgValue>
</operation>

<operation id="6" st_id="1" stage="1" lat="1">
<core>NULL</core>
<MemPortIdVec></MemPortIdVec>
<condition id="-1">
<or_exp><and_exp></and_exp></or_exp>
</condition>

<Node id="47" bw="16" op_0_bw="160">
<![CDATA[
ReLUActLoop:26  %tmp_data_V_8_2 = extractvalue { i16, i16, i16, i16, i16, i16, i16, i16, i16, i16 } %empty, 2

]]></Node>
<StgValue><ssdm name="tmp_data_V_8_2"/></StgValue>
</operation>

<operation id="7" st_id="1" stage="1" lat="1">
<core>NULL</core>
<MemPortIdVec></MemPortIdVec>
<condition id="-1">
<or_exp><and_exp></and_exp></or_exp>
</condition>

<Node id="48" bw="16" op_0_bw="160">
<![CDATA[
ReLUActLoop:27  %tmp_data_V_8_3 = extractvalue { i16, i16, i16, i16, i16, i16, i16, i16, i16, i16 } %empty, 3

]]></Node>
<StgValue><ssdm name="tmp_data_V_8_3"/></StgValue>
</operation>

<operation id="8" st_id="1" stage="1" lat="1">
<core>NULL</core>
<MemPortIdVec></MemPortIdVec>
<condition id="-1">
<or_exp><and_exp></and_exp></or_exp>
</condition>

<Node id="49" bw="16" op_0_bw="160">
<![CDATA[
ReLUActLoop:28  %tmp_data_V_8_4 = extractvalue { i16, i16, i16, i16, i16, i16, i16, i16, i16, i16 } %empty, 4

]]></Node>
<StgValue><ssdm name="tmp_data_V_8_4"/></StgValue>
</operation>

<operation id="9" st_id="1" stage="1" lat="1">
<core>NULL</core>
<MemPortIdVec></MemPortIdVec>
<condition id="-1">
<or_exp><and_exp></and_exp></or_exp>
</condition>

<Node id="50" bw="16" op_0_bw="160">
<![CDATA[
ReLUActLoop:29  %tmp_data_V_8_5 = extractvalue { i16, i16, i16, i16, i16, i16, i16, i16, i16, i16 } %empty, 5

]]></Node>
<StgValue><ssdm name="tmp_data_V_8_5"/></StgValue>
</operation>

<operation id="10" st_id="1" stage="1" lat="1">
<core>NULL</core>
<MemPortIdVec></MemPortIdVec>
<condition id="-1">
<or_exp><and_exp></and_exp></or_exp>
</condition>

<Node id="51" bw="16" op_0_bw="160">
<![CDATA[
ReLUActLoop:30  %tmp_data_V_8_6 = extractvalue { i16, i16, i16, i16, i16, i16, i16, i16, i16, i16 } %empty, 6

]]></Node>
<StgValue><ssdm name="tmp_data_V_8_6"/></StgValue>
</operation>

<operation id="11" st_id="1" stage="1" lat="1">
<core>NULL</core>
<MemPortIdVec></MemPortIdVec>
<condition id="-1">
<or_exp><and_exp></and_exp></or_exp>
</condition>

<Node id="52" bw="16" op_0_bw="160">
<![CDATA[
ReLUActLoop:31  %tmp_data_V_8_7 = extractvalue { i16, i16, i16, i16, i16, i16, i16, i16, i16, i16 } %empty, 7

]]></Node>
<StgValue><ssdm name="tmp_data_V_8_7"/></StgValue>
</operation>

<operation id="12" st_id="1" stage="1" lat="1">
<core>NULL</core>
<MemPortIdVec></MemPortIdVec>
<condition id="-1">
<or_exp><and_exp></and_exp></or_exp>
</condition>

<Node id="53" bw="16" op_0_bw="160">
<![CDATA[
ReLUActLoop:32  %tmp_data_V_8_8 = extractvalue { i16, i16, i16, i16, i16, i16, i16, i16, i16, i16 } %empty, 8

]]></Node>
<StgValue><ssdm name="tmp_data_V_8_8"/></StgValue>
</operation>

<operation id="13" st_id="1" stage="1" lat="1">
<core>NULL</core>
<MemPortIdVec></MemPortIdVec>
<condition id="-1">
<or_exp><and_exp></and_exp></or_exp>
</condition>

<Node id="54" bw="16" op_0_bw="160">
<![CDATA[
ReLUActLoop:33  %tmp_data_V_8_9 = extractvalue { i16, i16, i16, i16, i16, i16, i16, i16, i16, i16 } %empty, 9

]]></Node>
<StgValue><ssdm name="tmp_data_V_8_9"/></StgValue>
</operation>

<operation id="14" st_id="1" stage="1" lat="1">
<core>Cmp</core>
<MemPortIdVec></MemPortIdVec>
<condition id="-1">
<or_exp><and_exp></and_exp></or_exp>
</condition>

<Node id="55" bw="1" op_0_bw="16" op_1_bw="16">
<![CDATA[
ReLUActLoop:34  %icmp_ln1494 = icmp sgt i16 %tmp_data_V_8_0, 0

]]></Node>
<StgValue><ssdm name="icmp_ln1494"/></StgValue>
</operation>

<operation id="15" st_id="1" stage="1" lat="1">
<core>NULL</core>
<MemPortIdVec></MemPortIdVec>
<condition id="-1">
<or_exp><and_exp></and_exp></or_exp>
</condition>

<Node id="56" bw="8" op_0_bw="8" op_1_bw="16" op_2_bw="32" op_3_bw="32">
<![CDATA[
ReLUActLoop:35  %trunc_ln = call i8 @_ssdm_op_PartSelect.i8.i16.i32.i32(i16 %tmp_data_V_8_0, i32 4, i32 11)

]]></Node>
<StgValue><ssdm name="trunc_ln"/></StgValue>
</operation>

<operation id="16" st_id="1" stage="1" lat="1">
<core>Cmp</core>
<MemPortIdVec></MemPortIdVec>
<condition id="-1">
<or_exp><and_exp></and_exp></or_exp>
</condition>

<Node id="57" bw="1" op_0_bw="16" op_1_bw="16">
<![CDATA[
ReLUActLoop:36  %icmp_ln1494_1 = icmp sgt i16 %tmp_data_V_8_1, 0

]]></Node>
<StgValue><ssdm name="icmp_ln1494_1"/></StgValue>
</operation>

<operation id="17" st_id="1" stage="1" lat="1">
<core>NULL</core>
<MemPortIdVec></MemPortIdVec>
<condition id="-1">
<or_exp><and_exp></and_exp></or_exp>
</condition>

<Node id="58" bw="8" op_0_bw="8" op_1_bw="16" op_2_bw="32" op_3_bw="32">
<![CDATA[
ReLUActLoop:37  %trunc_ln708_1 = call i8 @_ssdm_op_PartSelect.i8.i16.i32.i32(i16 %tmp_data_V_8_1, i32 4, i32 11)

]]></Node>
<StgValue><ssdm name="trunc_ln708_1"/></StgValue>
</operation>

<operation id="18" st_id="1" stage="1" lat="1">
<core>Cmp</core>
<MemPortIdVec></MemPortIdVec>
<condition id="-1">
<or_exp><and_exp></and_exp></or_exp>
</condition>

<Node id="59" bw="1" op_0_bw="16" op_1_bw="16">
<![CDATA[
ReLUActLoop:38  %icmp_ln1494_2 = icmp sgt i16 %tmp_data_V_8_2, 0

]]></Node>
<StgValue><ssdm name="icmp_ln1494_2"/></StgValue>
</operation>

<operation id="19" st_id="1" stage="1" lat="1">
<core>NULL</core>
<MemPortIdVec></MemPortIdVec>
<condition id="-1">
<or_exp><and_exp></and_exp></or_exp>
</condition>

<Node id="60" bw="8" op_0_bw="8" op_1_bw="16" op_2_bw="32" op_3_bw="32">
<![CDATA[
ReLUActLoop:39  %trunc_ln708_2 = call i8 @_ssdm_op_PartSelect.i8.i16.i32.i32(i16 %tmp_data_V_8_2, i32 4, i32 11)

]]></Node>
<StgValue><ssdm name="trunc_ln708_2"/></StgValue>
</operation>

<operation id="20" st_id="1" stage="1" lat="1">
<core>Cmp</core>
<MemPortIdVec></MemPortIdVec>
<condition id="-1">
<or_exp><and_exp></and_exp></or_exp>
</condition>

<Node id="61" bw="1" op_0_bw="16" op_1_bw="16">
<![CDATA[
ReLUActLoop:40  %icmp_ln1494_3 = icmp sgt i16 %tmp_data_V_8_3, 0

]]></Node>
<StgValue><ssdm name="icmp_ln1494_3"/></StgValue>
</operation>

<operation id="21" st_id="1" stage="1" lat="1">
<core>NULL</core>
<MemPortIdVec></MemPortIdVec>
<condition id="-1">
<or_exp><and_exp></and_exp></or_exp>
</condition>

<Node id="62" bw="8" op_0_bw="8" op_1_bw="16" op_2_bw="32" op_3_bw="32">
<![CDATA[
ReLUActLoop:41  %trunc_ln708_3 = call i8 @_ssdm_op_PartSelect.i8.i16.i32.i32(i16 %tmp_data_V_8_3, i32 4, i32 11)

]]></Node>
<StgValue><ssdm name="trunc_ln708_3"/></StgValue>
</operation>

<operation id="22" st_id="1" stage="1" lat="1">
<core>Cmp</core>
<MemPortIdVec></MemPortIdVec>
<condition id="-1">
<or_exp><and_exp></and_exp></or_exp>
</condition>

<Node id="63" bw="1" op_0_bw="16" op_1_bw="16">
<![CDATA[
ReLUActLoop:42  %icmp_ln1494_4 = icmp sgt i16 %tmp_data_V_8_4, 0

]]></Node>
<StgValue><ssdm name="icmp_ln1494_4"/></StgValue>
</operation>

<operation id="23" st_id="1" stage="1" lat="1">
<core>NULL</core>
<MemPortIdVec></MemPortIdVec>
<condition id="-1">
<or_exp><and_exp></and_exp></or_exp>
</condition>

<Node id="64" bw="8" op_0_bw="8" op_1_bw="16" op_2_bw="32" op_3_bw="32">
<![CDATA[
ReLUActLoop:43  %trunc_ln708_4 = call i8 @_ssdm_op_PartSelect.i8.i16.i32.i32(i16 %tmp_data_V_8_4, i32 4, i32 11)

]]></Node>
<StgValue><ssdm name="trunc_ln708_4"/></StgValue>
</operation>

<operation id="24" st_id="1" stage="1" lat="1">
<core>Cmp</core>
<MemPortIdVec></MemPortIdVec>
<condition id="-1">
<or_exp><and_exp></and_exp></or_exp>
</condition>

<Node id="65" bw="1" op_0_bw="16" op_1_bw="16">
<![CDATA[
ReLUActLoop:44  %icmp_ln1494_5 = icmp sgt i16 %tmp_data_V_8_5, 0

]]></Node>
<StgValue><ssdm name="icmp_ln1494_5"/></StgValue>
</operation>

<operation id="25" st_id="1" stage="1" lat="1">
<core>NULL</core>
<MemPortIdVec></MemPortIdVec>
<condition id="-1">
<or_exp><and_exp></and_exp></or_exp>
</condition>

<Node id="66" bw="8" op_0_bw="8" op_1_bw="16" op_2_bw="32" op_3_bw="32">
<![CDATA[
ReLUActLoop:45  %trunc_ln708_5 = call i8 @_ssdm_op_PartSelect.i8.i16.i32.i32(i16 %tmp_data_V_8_5, i32 4, i32 11)

]]></Node>
<StgValue><ssdm name="trunc_ln708_5"/></StgValue>
</operation>

<operation id="26" st_id="1" stage="1" lat="1">
<core>Cmp</core>
<MemPortIdVec></MemPortIdVec>
<condition id="-1">
<or_exp><and_exp></and_exp></or_exp>
</condition>

<Node id="67" bw="1" op_0_bw="16" op_1_bw="16">
<![CDATA[
ReLUActLoop:46  %icmp_ln1494_6 = icmp sgt i16 %tmp_data_V_8_6, 0

]]></Node>
<StgValue><ssdm name="icmp_ln1494_6"/></StgValue>
</operation>

<operation id="27" st_id="1" stage="1" lat="1">
<core>NULL</core>
<MemPortIdVec></MemPortIdVec>
<condition id="-1">
<or_exp><and_exp></and_exp></or_exp>
</condition>

<Node id="68" bw="8" op_0_bw="8" op_1_bw="16" op_2_bw="32" op_3_bw="32">
<![CDATA[
ReLUActLoop:47  %trunc_ln708_6 = call i8 @_ssdm_op_PartSelect.i8.i16.i32.i32(i16 %tmp_data_V_8_6, i32 4, i32 11)

]]></Node>
<StgValue><ssdm name="trunc_ln708_6"/></StgValue>
</operation>

<operation id="28" st_id="1" stage="1" lat="1">
<core>Cmp</core>
<MemPortIdVec></MemPortIdVec>
<condition id="-1">
<or_exp><and_exp></and_exp></or_exp>
</condition>

<Node id="69" bw="1" op_0_bw="16" op_1_bw="16">
<![CDATA[
ReLUActLoop:48  %icmp_ln1494_7 = icmp sgt i16 %tmp_data_V_8_7, 0

]]></Node>
<StgValue><ssdm name="icmp_ln1494_7"/></StgValue>
</operation>

<operation id="29" st_id="1" stage="1" lat="1">
<core>NULL</core>
<MemPortIdVec></MemPortIdVec>
<condition id="-1">
<or_exp><and_exp></and_exp></or_exp>
</condition>

<Node id="70" bw="8" op_0_bw="8" op_1_bw="16" op_2_bw="32" op_3_bw="32">
<![CDATA[
ReLUActLoop:49  %trunc_ln708_7 = call i8 @_ssdm_op_PartSelect.i8.i16.i32.i32(i16 %tmp_data_V_8_7, i32 4, i32 11)

]]></Node>
<StgValue><ssdm name="trunc_ln708_7"/></StgValue>
</operation>

<operation id="30" st_id="1" stage="1" lat="1">
<core>Cmp</core>
<MemPortIdVec></MemPortIdVec>
<condition id="-1">
<or_exp><and_exp></and_exp></or_exp>
</condition>

<Node id="71" bw="1" op_0_bw="16" op_1_bw="16">
<![CDATA[
ReLUActLoop:50  %icmp_ln1494_8 = icmp sgt i16 %tmp_data_V_8_8, 0

]]></Node>
<StgValue><ssdm name="icmp_ln1494_8"/></StgValue>
</operation>

<operation id="31" st_id="1" stage="1" lat="1">
<core>NULL</core>
<MemPortIdVec></MemPortIdVec>
<condition id="-1">
<or_exp><and_exp></and_exp></or_exp>
</condition>

<Node id="72" bw="8" op_0_bw="8" op_1_bw="16" op_2_bw="32" op_3_bw="32">
<![CDATA[
ReLUActLoop:51  %trunc_ln708_8 = call i8 @_ssdm_op_PartSelect.i8.i16.i32.i32(i16 %tmp_data_V_8_8, i32 4, i32 11)

]]></Node>
<StgValue><ssdm name="trunc_ln708_8"/></StgValue>
</operation>

<operation id="32" st_id="1" stage="1" lat="1">
<core>Cmp</core>
<MemPortIdVec></MemPortIdVec>
<condition id="-1">
<or_exp><and_exp></and_exp></or_exp>
</condition>

<Node id="73" bw="1" op_0_bw="16" op_1_bw="16">
<![CDATA[
ReLUActLoop:52  %icmp_ln1494_9 = icmp sgt i16 %tmp_data_V_8_9, 0

]]></Node>
<StgValue><ssdm name="icmp_ln1494_9"/></StgValue>
</operation>

<operation id="33" st_id="1" stage="1" lat="1">
<core>NULL</core>
<MemPortIdVec></MemPortIdVec>
<condition id="-1">
<or_exp><and_exp></and_exp></or_exp>
</condition>

<Node id="74" bw="8" op_0_bw="8" op_1_bw="16" op_2_bw="32" op_3_bw="32">
<![CDATA[
ReLUActLoop:53  %trunc_ln708_9 = call i8 @_ssdm_op_PartSelect.i8.i16.i32.i32(i16 %tmp_data_V_8_9, i32 4, i32 11)

]]></Node>
<StgValue><ssdm name="trunc_ln708_9"/></StgValue>
</operation>

<operation id="34" st_id="1" stage="1" lat="1">
<core>Sel</core>
<MemPortIdVec></MemPortIdVec>
<condition id="-1">
<or_exp><and_exp></and_exp></or_exp>
</condition>

<Node id="75" bw="8" op_0_bw="1" op_1_bw="8" op_2_bw="8">
<![CDATA[
ReLUActLoop:54  %tmp_data_0_V = select i1 %icmp_ln1494, i8 %trunc_ln, i8 0

]]></Node>
<StgValue><ssdm name="tmp_data_0_V"/></StgValue>
</operation>

<operation id="35" st_id="1" stage="1" lat="1">
<core>Sel</core>
<MemPortIdVec></MemPortIdVec>
<condition id="-1">
<or_exp><and_exp></and_exp></or_exp>
</condition>

<Node id="76" bw="8" op_0_bw="1" op_1_bw="8" op_2_bw="8">
<![CDATA[
ReLUActLoop:55  %tmp_data_1_V = select i1 %icmp_ln1494_1, i8 %trunc_ln708_1, i8 0

]]></Node>
<StgValue><ssdm name="tmp_data_1_V"/></StgValue>
</operation>

<operation id="36" st_id="1" stage="1" lat="1">
<core>Sel</core>
<MemPortIdVec></MemPortIdVec>
<condition id="-1">
<or_exp><and_exp></and_exp></or_exp>
</condition>

<Node id="77" bw="8" op_0_bw="1" op_1_bw="8" op_2_bw="8">
<![CDATA[
ReLUActLoop:56  %tmp_data_2_V = select i1 %icmp_ln1494_2, i8 %trunc_ln708_2, i8 0

]]></Node>
<StgValue><ssdm name="tmp_data_2_V"/></StgValue>
</operation>

<operation id="37" st_id="1" stage="1" lat="1">
<core>Sel</core>
<MemPortIdVec></MemPortIdVec>
<condition id="-1">
<or_exp><and_exp></and_exp></or_exp>
</condition>

<Node id="78" bw="8" op_0_bw="1" op_1_bw="8" op_2_bw="8">
<![CDATA[
ReLUActLoop:57  %tmp_data_3_V = select i1 %icmp_ln1494_3, i8 %trunc_ln708_3, i8 0

]]></Node>
<StgValue><ssdm name="tmp_data_3_V"/></StgValue>
</operation>

<operation id="38" st_id="1" stage="1" lat="1">
<core>Sel</core>
<MemPortIdVec></MemPortIdVec>
<condition id="-1">
<or_exp><and_exp></and_exp></or_exp>
</condition>

<Node id="79" bw="8" op_0_bw="1" op_1_bw="8" op_2_bw="8">
<![CDATA[
ReLUActLoop:58  %tmp_data_4_V = select i1 %icmp_ln1494_4, i8 %trunc_ln708_4, i8 0

]]></Node>
<StgValue><ssdm name="tmp_data_4_V"/></StgValue>
</operation>

<operation id="39" st_id="1" stage="1" lat="1">
<core>Sel</core>
<MemPortIdVec></MemPortIdVec>
<condition id="-1">
<or_exp><and_exp></and_exp></or_exp>
</condition>

<Node id="80" bw="8" op_0_bw="1" op_1_bw="8" op_2_bw="8">
<![CDATA[
ReLUActLoop:59  %tmp_data_5_V = select i1 %icmp_ln1494_5, i8 %trunc_ln708_5, i8 0

]]></Node>
<StgValue><ssdm name="tmp_data_5_V"/></StgValue>
</operation>

<operation id="40" st_id="1" stage="1" lat="1">
<core>Sel</core>
<MemPortIdVec></MemPortIdVec>
<condition id="-1">
<or_exp><and_exp></and_exp></or_exp>
</condition>

<Node id="81" bw="8" op_0_bw="1" op_1_bw="8" op_2_bw="8">
<![CDATA[
ReLUActLoop:60  %tmp_data_6_V = select i1 %icmp_ln1494_6, i8 %trunc_ln708_6, i8 0

]]></Node>
<StgValue><ssdm name="tmp_data_6_V"/></StgValue>
</operation>

<operation id="41" st_id="1" stage="1" lat="1">
<core>Sel</core>
<MemPortIdVec></MemPortIdVec>
<condition id="-1">
<or_exp><and_exp></and_exp></or_exp>
</condition>

<Node id="82" bw="8" op_0_bw="1" op_1_bw="8" op_2_bw="8">
<![CDATA[
ReLUActLoop:61  %tmp_data_7_V = select i1 %icmp_ln1494_7, i8 %trunc_ln708_7, i8 0

]]></Node>
<StgValue><ssdm name="tmp_data_7_V"/></StgValue>
</operation>

<operation id="42" st_id="1" stage="1" lat="1">
<core>Sel</core>
<MemPortIdVec></MemPortIdVec>
<condition id="-1">
<or_exp><and_exp></and_exp></or_exp>
</condition>

<Node id="83" bw="8" op_0_bw="1" op_1_bw="8" op_2_bw="8">
<![CDATA[
ReLUActLoop:62  %tmp_data_8_V = select i1 %icmp_ln1494_8, i8 %trunc_ln708_8, i8 0

]]></Node>
<StgValue><ssdm name="tmp_data_8_V"/></StgValue>
</operation>

<operation id="43" st_id="1" stage="1" lat="1">
<core>Sel</core>
<MemPortIdVec></MemPortIdVec>
<condition id="-1">
<or_exp><and_exp></and_exp></or_exp>
</condition>

<Node id="84" bw="8" op_0_bw="1" op_1_bw="8" op_2_bw="8">
<![CDATA[
ReLUActLoop:63  %tmp_data_9_V = select i1 %icmp_ln1494_9, i8 %trunc_ln708_9, i8 0

]]></Node>
<StgValue><ssdm name="tmp_data_9_V"/></StgValue>
</operation>
</state>

<state id="2" st_id="2">

<operation id="44" st_id="2" stage="1" lat="1">
<core>NULL</core>
<MemPortIdVec></MemPortIdVec>
<condition id="-1">
<or_exp><and_exp></and_exp></or_exp>
</condition>

<Node id="21" bw="0" op_0_bw="0" op_1_bw="8" op_2_bw="0" op_3_bw="32" op_4_bw="32" op_5_bw="0" op_6_bw="32" op_7_bw="32" op_8_bw="0" op_9_bw="0" op_10_bw="0" op_11_bw="32" op_12_bw="32" op_13_bw="32" op_14_bw="32" op_15_bw="0" op_16_bw="0">
<![CDATA[
ReLUActLoop:0  call void (...)* @_ssdm_op_SpecInterface(i8* %res_V_data_9_V, [8 x i8]* @ap_fifo_str, i32 0, i32 0, [1 x i8]* @p_str1693, i32 0, i32 0, [1 x i8]* @p_str1694, [1 x i8]* @p_str1695, [1 x i8]* @p_str1696, i32 2, i32 2, i32 16, i32 16, [1 x i8]* @p_str1697, [1 x i8]* @p_str1698)

]]></Node>
<StgValue><ssdm name="specinterface_ln0"/></StgValue>
</operation>

<operation id="45" st_id="2" stage="1" lat="1">
<core>NULL</core>
<MemPortIdVec></MemPortIdVec>
<condition id="-1">
<or_exp><and_exp></and_exp></or_exp>
</condition>

<Node id="22" bw="0" op_0_bw="0" op_1_bw="8" op_2_bw="0" op_3_bw="32" op_4_bw="32" op_5_bw="0" op_6_bw="32" op_7_bw="32" op_8_bw="0" op_9_bw="0" op_10_bw="0" op_11_bw="32" op_12_bw="32" op_13_bw="32" op_14_bw="32" op_15_bw="0" op_16_bw="0">
<![CDATA[
ReLUActLoop:1  call void (...)* @_ssdm_op_SpecInterface(i8* %res_V_data_8_V, [8 x i8]* @ap_fifo_str, i32 0, i32 0, [1 x i8]* @p_str1686, i32 0, i32 0, [1 x i8]* @p_str1687, [1 x i8]* @p_str1688, [1 x i8]* @p_str1689, i32 2, i32 2, i32 16, i32 16, [1 x i8]* @p_str1690, [1 x i8]* @p_str1691)

]]></Node>
<StgValue><ssdm name="specinterface_ln0"/></StgValue>
</operation>

<operation id="46" st_id="2" stage="1" lat="1">
<core>NULL</core>
<MemPortIdVec></MemPortIdVec>
<condition id="-1">
<or_exp><and_exp></and_exp></or_exp>
</condition>

<Node id="23" bw="0" op_0_bw="0" op_1_bw="8" op_2_bw="0" op_3_bw="32" op_4_bw="32" op_5_bw="0" op_6_bw="32" op_7_bw="32" op_8_bw="0" op_9_bw="0" op_10_bw="0" op_11_bw="32" op_12_bw="32" op_13_bw="32" op_14_bw="32" op_15_bw="0" op_16_bw="0">
<![CDATA[
ReLUActLoop:2  call void (...)* @_ssdm_op_SpecInterface(i8* %res_V_data_7_V, [8 x i8]* @ap_fifo_str, i32 0, i32 0, [1 x i8]* @p_str1679, i32 0, i32 0, [1 x i8]* @p_str1680, [1 x i8]* @p_str1681, [1 x i8]* @p_str1682, i32 2, i32 2, i32 16, i32 16, [1 x i8]* @p_str1683, [1 x i8]* @p_str1684)

]]></Node>
<StgValue><ssdm name="specinterface_ln0"/></StgValue>
</operation>

<operation id="47" st_id="2" stage="1" lat="1">
<core>NULL</core>
<MemPortIdVec></MemPortIdVec>
<condition id="-1">
<or_exp><and_exp></and_exp></or_exp>
</condition>

<Node id="24" bw="0" op_0_bw="0" op_1_bw="8" op_2_bw="0" op_3_bw="32" op_4_bw="32" op_5_bw="0" op_6_bw="32" op_7_bw="32" op_8_bw="0" op_9_bw="0" op_10_bw="0" op_11_bw="32" op_12_bw="32" op_13_bw="32" op_14_bw="32" op_15_bw="0" op_16_bw="0">
<![CDATA[
ReLUActLoop:3  call void (...)* @_ssdm_op_SpecInterface(i8* %res_V_data_6_V, [8 x i8]* @ap_fifo_str, i32 0, i32 0, [1 x i8]* @p_str1672, i32 0, i32 0, [1 x i8]* @p_str1673, [1 x i8]* @p_str1674, [1 x i8]* @p_str1675, i32 2, i32 2, i32 16, i32 16, [1 x i8]* @p_str1676, [1 x i8]* @p_str1677)

]]></Node>
<StgValue><ssdm name="specinterface_ln0"/></StgValue>
</operation>

<operation id="48" st_id="2" stage="1" lat="1">
<core>NULL</core>
<MemPortIdVec></MemPortIdVec>
<condition id="-1">
<or_exp><and_exp></and_exp></or_exp>
</condition>

<Node id="25" bw="0" op_0_bw="0" op_1_bw="8" op_2_bw="0" op_3_bw="32" op_4_bw="32" op_5_bw="0" op_6_bw="32" op_7_bw="32" op_8_bw="0" op_9_bw="0" op_10_bw="0" op_11_bw="32" op_12_bw="32" op_13_bw="32" op_14_bw="32" op_15_bw="0" op_16_bw="0">
<![CDATA[
ReLUActLoop:4  call void (...)* @_ssdm_op_SpecInterface(i8* %res_V_data_5_V, [8 x i8]* @ap_fifo_str, i32 0, i32 0, [1 x i8]* @p_str1665, i32 0, i32 0, [1 x i8]* @p_str1666, [1 x i8]* @p_str1667, [1 x i8]* @p_str1668, i32 2, i32 2, i32 16, i32 16, [1 x i8]* @p_str1669, [1 x i8]* @p_str1670)

]]></Node>
<StgValue><ssdm name="specinterface_ln0"/></StgValue>
</operation>

<operation id="49" st_id="2" stage="1" lat="1">
<core>NULL</core>
<MemPortIdVec></MemPortIdVec>
<condition id="-1">
<or_exp><and_exp></and_exp></or_exp>
</condition>

<Node id="26" bw="0" op_0_bw="0" op_1_bw="8" op_2_bw="0" op_3_bw="32" op_4_bw="32" op_5_bw="0" op_6_bw="32" op_7_bw="32" op_8_bw="0" op_9_bw="0" op_10_bw="0" op_11_bw="32" op_12_bw="32" op_13_bw="32" op_14_bw="32" op_15_bw="0" op_16_bw="0">
<![CDATA[
ReLUActLoop:5  call void (...)* @_ssdm_op_SpecInterface(i8* %res_V_data_4_V, [8 x i8]* @ap_fifo_str, i32 0, i32 0, [1 x i8]* @p_str1658, i32 0, i32 0, [1 x i8]* @p_str1659, [1 x i8]* @p_str1660, [1 x i8]* @p_str1661, i32 2, i32 2, i32 16, i32 16, [1 x i8]* @p_str1662, [1 x i8]* @p_str1663)

]]></Node>
<StgValue><ssdm name="specinterface_ln0"/></StgValue>
</operation>

<operation id="50" st_id="2" stage="1" lat="1">
<core>NULL</core>
<MemPortIdVec></MemPortIdVec>
<condition id="-1">
<or_exp><and_exp></and_exp></or_exp>
</condition>

<Node id="27" bw="0" op_0_bw="0" op_1_bw="8" op_2_bw="0" op_3_bw="32" op_4_bw="32" op_5_bw="0" op_6_bw="32" op_7_bw="32" op_8_bw="0" op_9_bw="0" op_10_bw="0" op_11_bw="32" op_12_bw="32" op_13_bw="32" op_14_bw="32" op_15_bw="0" op_16_bw="0">
<![CDATA[
ReLUActLoop:6  call void (...)* @_ssdm_op_SpecInterface(i8* %res_V_data_3_V, [8 x i8]* @ap_fifo_str, i32 0, i32 0, [1 x i8]* @p_str1651, i32 0, i32 0, [1 x i8]* @p_str1652, [1 x i8]* @p_str1653, [1 x i8]* @p_str1654, i32 2, i32 2, i32 16, i32 16, [1 x i8]* @p_str1655, [1 x i8]* @p_str1656)

]]></Node>
<StgValue><ssdm name="specinterface_ln0"/></StgValue>
</operation>

<operation id="51" st_id="2" stage="1" lat="1">
<core>NULL</core>
<MemPortIdVec></MemPortIdVec>
<condition id="-1">
<or_exp><and_exp></and_exp></or_exp>
</condition>

<Node id="28" bw="0" op_0_bw="0" op_1_bw="8" op_2_bw="0" op_3_bw="32" op_4_bw="32" op_5_bw="0" op_6_bw="32" op_7_bw="32" op_8_bw="0" op_9_bw="0" op_10_bw="0" op_11_bw="32" op_12_bw="32" op_13_bw="32" op_14_bw="32" op_15_bw="0" op_16_bw="0">
<![CDATA[
ReLUActLoop:7  call void (...)* @_ssdm_op_SpecInterface(i8* %res_V_data_2_V, [8 x i8]* @ap_fifo_str, i32 0, i32 0, [1 x i8]* @p_str1644, i32 0, i32 0, [1 x i8]* @p_str1645, [1 x i8]* @p_str1646, [1 x i8]* @p_str1647, i32 2, i32 2, i32 16, i32 16, [1 x i8]* @p_str1648, [1 x i8]* @p_str1649)

]]></Node>
<StgValue><ssdm name="specinterface_ln0"/></StgValue>
</operation>

<operation id="52" st_id="2" stage="1" lat="1">
<core>NULL</core>
<MemPortIdVec></MemPortIdVec>
<condition id="-1">
<or_exp><and_exp></and_exp></or_exp>
</condition>

<Node id="29" bw="0" op_0_bw="0" op_1_bw="8" op_2_bw="0" op_3_bw="32" op_4_bw="32" op_5_bw="0" op_6_bw="32" op_7_bw="32" op_8_bw="0" op_9_bw="0" op_10_bw="0" op_11_bw="32" op_12_bw="32" op_13_bw="32" op_14_bw="32" op_15_bw="0" op_16_bw="0">
<![CDATA[
ReLUActLoop:8  call void (...)* @_ssdm_op_SpecInterface(i8* %res_V_data_1_V, [8 x i8]* @ap_fifo_str, i32 0, i32 0, [1 x i8]* @p_str1637, i32 0, i32 0, [1 x i8]* @p_str1638, [1 x i8]* @p_str1639, [1 x i8]* @p_str1640, i32 2, i32 2, i32 16, i32 16, [1 x i8]* @p_str1641, [1 x i8]* @p_str1642)

]]></Node>
<StgValue><ssdm name="specinterface_ln0"/></StgValue>
</operation>

<operation id="53" st_id="2" stage="1" lat="1">
<core>NULL</core>
<MemPortIdVec></MemPortIdVec>
<condition id="-1">
<or_exp><and_exp></and_exp></or_exp>
</condition>

<Node id="30" bw="0" op_0_bw="0" op_1_bw="8" op_2_bw="0" op_3_bw="32" op_4_bw="32" op_5_bw="0" op_6_bw="32" op_7_bw="32" op_8_bw="0" op_9_bw="0" op_10_bw="0" op_11_bw="32" op_12_bw="32" op_13_bw="32" op_14_bw="32" op_15_bw="0" op_16_bw="0">
<![CDATA[
ReLUActLoop:9  call void (...)* @_ssdm_op_SpecInterface(i8* %res_V_data_0_V, [8 x i8]* @ap_fifo_str, i32 0, i32 0, [1 x i8]* @p_str1630, i32 0, i32 0, [1 x i8]* @p_str1631, [1 x i8]* @p_str1632, [1 x i8]* @p_str1633, i32 2, i32 2, i32 16, i32 16, [1 x i8]* @p_str1634, [1 x i8]* @p_str1635)

]]></Node>
<StgValue><ssdm name="specinterface_ln0"/></StgValue>
</operation>

<operation id="54" st_id="2" stage="1" lat="1">
<core>NULL</core>
<MemPortIdVec></MemPortIdVec>
<condition id="-1">
<or_exp><and_exp></and_exp></or_exp>
</condition>

<Node id="31" bw="0" op_0_bw="0" op_1_bw="16" op_2_bw="0" op_3_bw="32" op_4_bw="32" op_5_bw="0" op_6_bw="32" op_7_bw="32" op_8_bw="0" op_9_bw="0" op_10_bw="0" op_11_bw="32" op_12_bw="32" op_13_bw="32" op_14_bw="32" op_15_bw="0" op_16_bw="0">
<![CDATA[
ReLUActLoop:10  call void (...)* @_ssdm_op_SpecInterface(i16* %data_V_data_9_V, [8 x i8]* @ap_fifo_str, i32 0, i32 0, [1 x i8]* @p_str1623, i32 0, i32 0, [1 x i8]* @p_str1624, [1 x i8]* @p_str1625, [1 x i8]* @p_str1626, i32 2, i32 2, i32 16, i32 16, [1 x i8]* @p_str1627, [1 x i8]* @p_str1628)

]]></Node>
<StgValue><ssdm name="specinterface_ln0"/></StgValue>
</operation>

<operation id="55" st_id="2" stage="1" lat="1">
<core>NULL</core>
<MemPortIdVec></MemPortIdVec>
<condition id="-1">
<or_exp><and_exp></and_exp></or_exp>
</condition>

<Node id="32" bw="0" op_0_bw="0" op_1_bw="16" op_2_bw="0" op_3_bw="32" op_4_bw="32" op_5_bw="0" op_6_bw="32" op_7_bw="32" op_8_bw="0" op_9_bw="0" op_10_bw="0" op_11_bw="32" op_12_bw="32" op_13_bw="32" op_14_bw="32" op_15_bw="0" op_16_bw="0">
<![CDATA[
ReLUActLoop:11  call void (...)* @_ssdm_op_SpecInterface(i16* %data_V_data_8_V, [8 x i8]* @ap_fifo_str, i32 0, i32 0, [1 x i8]* @p_str1616, i32 0, i32 0, [1 x i8]* @p_str1617, [1 x i8]* @p_str1618, [1 x i8]* @p_str1619, i32 2, i32 2, i32 16, i32 16, [1 x i8]* @p_str1620, [1 x i8]* @p_str1621)

]]></Node>
<StgValue><ssdm name="specinterface_ln0"/></StgValue>
</operation>

<operation id="56" st_id="2" stage="1" lat="1">
<core>NULL</core>
<MemPortIdVec></MemPortIdVec>
<condition id="-1">
<or_exp><and_exp></and_exp></or_exp>
</condition>

<Node id="33" bw="0" op_0_bw="0" op_1_bw="16" op_2_bw="0" op_3_bw="32" op_4_bw="32" op_5_bw="0" op_6_bw="32" op_7_bw="32" op_8_bw="0" op_9_bw="0" op_10_bw="0" op_11_bw="32" op_12_bw="32" op_13_bw="32" op_14_bw="32" op_15_bw="0" op_16_bw="0">
<![CDATA[
ReLUActLoop:12  call void (...)* @_ssdm_op_SpecInterface(i16* %data_V_data_7_V, [8 x i8]* @ap_fifo_str, i32 0, i32 0, [1 x i8]* @p_str1609, i32 0, i32 0, [1 x i8]* @p_str1610, [1 x i8]* @p_str1611, [1 x i8]* @p_str1612, i32 2, i32 2, i32 16, i32 16, [1 x i8]* @p_str1613, [1 x i8]* @p_str1614)

]]></Node>
<StgValue><ssdm name="specinterface_ln0"/></StgValue>
</operation>

<operation id="57" st_id="2" stage="1" lat="1">
<core>NULL</core>
<MemPortIdVec></MemPortIdVec>
<condition id="-1">
<or_exp><and_exp></and_exp></or_exp>
</condition>

<Node id="34" bw="0" op_0_bw="0" op_1_bw="16" op_2_bw="0" op_3_bw="32" op_4_bw="32" op_5_bw="0" op_6_bw="32" op_7_bw="32" op_8_bw="0" op_9_bw="0" op_10_bw="0" op_11_bw="32" op_12_bw="32" op_13_bw="32" op_14_bw="32" op_15_bw="0" op_16_bw="0">
<![CDATA[
ReLUActLoop:13  call void (...)* @_ssdm_op_SpecInterface(i16* %data_V_data_6_V, [8 x i8]* @ap_fifo_str, i32 0, i32 0, [1 x i8]* @p_str1602, i32 0, i32 0, [1 x i8]* @p_str1603, [1 x i8]* @p_str1604, [1 x i8]* @p_str1605, i32 2, i32 2, i32 16, i32 16, [1 x i8]* @p_str1606, [1 x i8]* @p_str1607)

]]></Node>
<StgValue><ssdm name="specinterface_ln0"/></StgValue>
</operation>

<operation id="58" st_id="2" stage="1" lat="1">
<core>NULL</core>
<MemPortIdVec></MemPortIdVec>
<condition id="-1">
<or_exp><and_exp></and_exp></or_exp>
</condition>

<Node id="35" bw="0" op_0_bw="0" op_1_bw="16" op_2_bw="0" op_3_bw="32" op_4_bw="32" op_5_bw="0" op_6_bw="32" op_7_bw="32" op_8_bw="0" op_9_bw="0" op_10_bw="0" op_11_bw="32" op_12_bw="32" op_13_bw="32" op_14_bw="32" op_15_bw="0" op_16_bw="0">
<![CDATA[
ReLUActLoop:14  call void (...)* @_ssdm_op_SpecInterface(i16* %data_V_data_5_V, [8 x i8]* @ap_fifo_str, i32 0, i32 0, [1 x i8]* @p_str1595, i32 0, i32 0, [1 x i8]* @p_str1596, [1 x i8]* @p_str1597, [1 x i8]* @p_str1598, i32 2, i32 2, i32 16, i32 16, [1 x i8]* @p_str1599, [1 x i8]* @p_str1600)

]]></Node>
<StgValue><ssdm name="specinterface_ln0"/></StgValue>
</operation>

<operation id="59" st_id="2" stage="1" lat="1">
<core>NULL</core>
<MemPortIdVec></MemPortIdVec>
<condition id="-1">
<or_exp><and_exp></and_exp></or_exp>
</condition>

<Node id="36" bw="0" op_0_bw="0" op_1_bw="16" op_2_bw="0" op_3_bw="32" op_4_bw="32" op_5_bw="0" op_6_bw="32" op_7_bw="32" op_8_bw="0" op_9_bw="0" op_10_bw="0" op_11_bw="32" op_12_bw="32" op_13_bw="32" op_14_bw="32" op_15_bw="0" op_16_bw="0">
<![CDATA[
ReLUActLoop:15  call void (...)* @_ssdm_op_SpecInterface(i16* %data_V_data_4_V, [8 x i8]* @ap_fifo_str, i32 0, i32 0, [1 x i8]* @p_str1588, i32 0, i32 0, [1 x i8]* @p_str1589, [1 x i8]* @p_str1590, [1 x i8]* @p_str1591, i32 2, i32 2, i32 16, i32 16, [1 x i8]* @p_str1592, [1 x i8]* @p_str1593)

]]></Node>
<StgValue><ssdm name="specinterface_ln0"/></StgValue>
</operation>

<operation id="60" st_id="2" stage="1" lat="1">
<core>NULL</core>
<MemPortIdVec></MemPortIdVec>
<condition id="-1">
<or_exp><and_exp></and_exp></or_exp>
</condition>

<Node id="37" bw="0" op_0_bw="0" op_1_bw="16" op_2_bw="0" op_3_bw="32" op_4_bw="32" op_5_bw="0" op_6_bw="32" op_7_bw="32" op_8_bw="0" op_9_bw="0" op_10_bw="0" op_11_bw="32" op_12_bw="32" op_13_bw="32" op_14_bw="32" op_15_bw="0" op_16_bw="0">
<![CDATA[
ReLUActLoop:16  call void (...)* @_ssdm_op_SpecInterface(i16* %data_V_data_3_V, [8 x i8]* @ap_fifo_str, i32 0, i32 0, [1 x i8]* @p_str1581, i32 0, i32 0, [1 x i8]* @p_str1582, [1 x i8]* @p_str1583, [1 x i8]* @p_str1584, i32 2, i32 2, i32 16, i32 16, [1 x i8]* @p_str1585, [1 x i8]* @p_str1586)

]]></Node>
<StgValue><ssdm name="specinterface_ln0"/></StgValue>
</operation>

<operation id="61" st_id="2" stage="1" lat="1">
<core>NULL</core>
<MemPortIdVec></MemPortIdVec>
<condition id="-1">
<or_exp><and_exp></and_exp></or_exp>
</condition>

<Node id="38" bw="0" op_0_bw="0" op_1_bw="16" op_2_bw="0" op_3_bw="32" op_4_bw="32" op_5_bw="0" op_6_bw="32" op_7_bw="32" op_8_bw="0" op_9_bw="0" op_10_bw="0" op_11_bw="32" op_12_bw="32" op_13_bw="32" op_14_bw="32" op_15_bw="0" op_16_bw="0">
<![CDATA[
ReLUActLoop:17  call void (...)* @_ssdm_op_SpecInterface(i16* %data_V_data_2_V, [8 x i8]* @ap_fifo_str, i32 0, i32 0, [1 x i8]* @p_str1574, i32 0, i32 0, [1 x i8]* @p_str1575, [1 x i8]* @p_str1576, [1 x i8]* @p_str1577, i32 2, i32 2, i32 16, i32 16, [1 x i8]* @p_str1578, [1 x i8]* @p_str1579)

]]></Node>
<StgValue><ssdm name="specinterface_ln0"/></StgValue>
</operation>

<operation id="62" st_id="2" stage="1" lat="1">
<core>NULL</core>
<MemPortIdVec></MemPortIdVec>
<condition id="-1">
<or_exp><and_exp></and_exp></or_exp>
</condition>

<Node id="39" bw="0" op_0_bw="0" op_1_bw="16" op_2_bw="0" op_3_bw="32" op_4_bw="32" op_5_bw="0" op_6_bw="32" op_7_bw="32" op_8_bw="0" op_9_bw="0" op_10_bw="0" op_11_bw="32" op_12_bw="32" op_13_bw="32" op_14_bw="32" op_15_bw="0" op_16_bw="0">
<![CDATA[
ReLUActLoop:18  call void (...)* @_ssdm_op_SpecInterface(i16* %data_V_data_1_V, [8 x i8]* @ap_fifo_str, i32 0, i32 0, [1 x i8]* @p_str1567, i32 0, i32 0, [1 x i8]* @p_str1568, [1 x i8]* @p_str1569, [1 x i8]* @p_str1570, i32 2, i32 2, i32 16, i32 16, [1 x i8]* @p_str1571, [1 x i8]* @p_str1572)

]]></Node>
<StgValue><ssdm name="specinterface_ln0"/></StgValue>
</operation>

<operation id="63" st_id="2" stage="1" lat="1">
<core>NULL</core>
<MemPortIdVec></MemPortIdVec>
<condition id="-1">
<or_exp><and_exp></and_exp></or_exp>
</condition>

<Node id="40" bw="0" op_0_bw="0" op_1_bw="16" op_2_bw="0" op_3_bw="32" op_4_bw="32" op_5_bw="0" op_6_bw="32" op_7_bw="32" op_8_bw="0" op_9_bw="0" op_10_bw="0" op_11_bw="32" op_12_bw="32" op_13_bw="32" op_14_bw="32" op_15_bw="0" op_16_bw="0">
<![CDATA[
ReLUActLoop:19  call void (...)* @_ssdm_op_SpecInterface(i16* %data_V_data_0_V, [8 x i8]* @ap_fifo_str, i32 0, i32 0, [1 x i8]* @p_str1560, i32 0, i32 0, [1 x i8]* @p_str1561, [1 x i8]* @p_str1562, [1 x i8]* @p_str1563, i32 2, i32 2, i32 16, i32 16, [1 x i8]* @p_str1564, [1 x i8]* @p_str1565)

]]></Node>
<StgValue><ssdm name="specinterface_ln0"/></StgValue>
</operation>

<operation id="64" st_id="2" stage="1" lat="1">
<core>NULL</core>
<MemPortIdVec></MemPortIdVec>
<condition id="-1">
<or_exp><and_exp></and_exp></or_exp>
</condition>

<Node id="41" bw="0" op_0_bw="0" op_1_bw="0">
<![CDATA[
ReLUActLoop:20  call void (...)* @_ssdm_op_SpecLoopName([12 x i8]* @p_str56) nounwind

]]></Node>
<StgValue><ssdm name="specloopname_ln41"/></StgValue>
</operation>

<operation id="65" st_id="2" stage="1" lat="1">
<core>NULL</core>
<MemPortIdVec></MemPortIdVec>
<condition id="-1">
<or_exp><and_exp></and_exp></or_exp>
</condition>

<Node id="42" bw="32" op_0_bw="32" op_1_bw="0">
<![CDATA[
ReLUActLoop:21  %tmp = call i32 (...)* @_ssdm_op_SpecRegionBegin([12 x i8]* @p_str56)

]]></Node>
<StgValue><ssdm name="tmp"/></StgValue>
</operation>

<operation id="66" st_id="2" stage="1" lat="1">
<core>NULL</core>
<MemPortIdVec></MemPortIdVec>
<condition id="-1">
<or_exp><and_exp></and_exp></or_exp>
</condition>

<Node id="43" bw="0" op_0_bw="0" op_1_bw="32" op_2_bw="32" op_3_bw="32" op_4_bw="32" op_5_bw="0">
<![CDATA[
ReLUActLoop:22  call void (...)* @_ssdm_op_SpecPipeline(i32 -1, i32 1, i32 1, i32 0, [1 x i8]* @p_str17) nounwind

]]></Node>
<StgValue><ssdm name="specpipeline_ln42"/></StgValue>
</operation>

<operation id="67" st_id="2" stage="1" lat="1">
<core>FIFO</core>
<MemPortIdVec></MemPortIdVec>
<condition id="-1">
<or_exp><and_exp></and_exp></or_exp>
</condition>

<Node id="85" bw="0" op_0_bw="0" op_1_bw="8" op_2_bw="8" op_3_bw="8" op_4_bw="8" op_5_bw="8" op_6_bw="8" op_7_bw="8" op_8_bw="8" op_9_bw="8" op_10_bw="8" op_11_bw="8" op_12_bw="8" op_13_bw="8" op_14_bw="8" op_15_bw="8" op_16_bw="8" op_17_bw="8" op_18_bw="8" op_19_bw="8" op_20_bw="8">
<![CDATA[
ReLUActLoop:64  call void @_ssdm_op_Write.ap_fifo.volatile.i8P.i8P.i8P.i8P.i8P.i8P.i8P.i8P.i8P.i8P(i8* %res_V_data_0_V, i8* %res_V_data_1_V, i8* %res_V_data_2_V, i8* %res_V_data_3_V, i8* %res_V_data_4_V, i8* %res_V_data_5_V, i8* %res_V_data_6_V, i8* %res_V_data_7_V, i8* %res_V_data_8_V, i8* %res_V_data_9_V, i8 %tmp_data_0_V, i8 %tmp_data_1_V, i8 %tmp_data_2_V, i8 %tmp_data_3_V, i8 %tmp_data_4_V, i8 %tmp_data_5_V, i8 %tmp_data_6_V, i8 %tmp_data_7_V, i8 %tmp_data_8_V, i8 %tmp_data_9_V)

]]></Node>
<StgValue><ssdm name="write_ln57"/></StgValue>
</operation>

<operation id="68" st_id="2" stage="1" lat="1">
<core>NULL</core>
<MemPortIdVec></MemPortIdVec>
<condition id="-1">
<or_exp><and_exp></and_exp></or_exp>
</condition>

<Node id="86" bw="32" op_0_bw="32" op_1_bw="0" op_2_bw="32">
<![CDATA[
ReLUActLoop:65  %empty_34 = call i32 (...)* @_ssdm_op_SpecRegionEnd([12 x i8]* @p_str56, i32 %tmp)

]]></Node>
<StgValue><ssdm name="empty_34"/></StgValue>
</operation>

<operation id="69" st_id="2" stage="1" lat="1">
<core>NULL</core>
<MemPortIdVec></MemPortIdVec>
<condition id="-1">
<or_exp><and_exp></and_exp></or_exp>
</condition>

<Node id="87" bw="0">
<![CDATA[
ReLUActLoop:66  ret void

]]></Node>
<StgValue><ssdm name="ret_ln59"/></StgValue>
</operation>
</state>
</state_list>


<ports>
<port id="73" name="data_V_data_0_V" dir="0" iftype="3">
<core>FIFO</core><StgValue><ssdm name="data_V_data_0_V"/></StgValue>
</port>
<port id="74" name="data_V_data_1_V" dir="0" iftype="3">
<core>FIFO</core><StgValue><ssdm name="data_V_data_1_V"/></StgValue>
</port>
<port id="75" name="data_V_data_2_V" dir="0" iftype="3">
<core>FIFO</core><StgValue><ssdm name="data_V_data_2_V"/></StgValue>
</port>
<port id="76" name="data_V_data_3_V" dir="0" iftype="3">
<core>FIFO</core><StgValue><ssdm name="data_V_data_3_V"/></StgValue>
</port>
<port id="77" name="data_V_data_4_V" dir="0" iftype="3">
<core>FIFO</core><StgValue><ssdm name="data_V_data_4_V"/></StgValue>
</port>
<port id="78" name="data_V_data_5_V" dir="0" iftype="3">
<core>FIFO</core><StgValue><ssdm name="data_V_data_5_V"/></StgValue>
</port>
<port id="79" name="data_V_data_6_V" dir="0" iftype="3">
<core>FIFO</core><StgValue><ssdm name="data_V_data_6_V"/></StgValue>
</port>
<port id="80" name="data_V_data_7_V" dir="0" iftype="3">
<core>FIFO</core><StgValue><ssdm name="data_V_data_7_V"/></StgValue>
</port>
<port id="81" name="data_V_data_8_V" dir="0" iftype="3">
<core>FIFO</core><StgValue><ssdm name="data_V_data_8_V"/></StgValue>
</port>
<port id="82" name="data_V_data_9_V" dir="0" iftype="3">
<core>FIFO</core><StgValue><ssdm name="data_V_data_9_V"/></StgValue>
</port>
<port id="83" name="res_V_data_0_V" dir="1" iftype="3">
<core>FIFO</core><StgValue><ssdm name="res_V_data_0_V"/></StgValue>
</port>
<port id="84" name="res_V_data_1_V" dir="1" iftype="3">
<core>FIFO</core><StgValue><ssdm name="res_V_data_1_V"/></StgValue>
</port>
<port id="85" name="res_V_data_2_V" dir="1" iftype="3">
<core>FIFO</core><StgValue><ssdm name="res_V_data_2_V"/></StgValue>
</port>
<port id="86" name="res_V_data_3_V" dir="1" iftype="3">
<core>FIFO</core><StgValue><ssdm name="res_V_data_3_V"/></StgValue>
</port>
<port id="87" name="res_V_data_4_V" dir="1" iftype="3">
<core>FIFO</core><StgValue><ssdm name="res_V_data_4_V"/></StgValue>
</port>
<port id="88" name="res_V_data_5_V" dir="1" iftype="3">
<core>FIFO</core><StgValue><ssdm name="res_V_data_5_V"/></StgValue>
</port>
<port id="89" name="res_V_data_6_V" dir="1" iftype="3">
<core>FIFO</core><StgValue><ssdm name="res_V_data_6_V"/></StgValue>
</port>
<port id="90" name="res_V_data_7_V" dir="1" iftype="3">
<core>FIFO</core><StgValue><ssdm name="res_V_data_7_V"/></StgValue>
</port>
<port id="91" name="res_V_data_8_V" dir="1" iftype="3">
<core>FIFO</core><StgValue><ssdm name="res_V_data_8_V"/></StgValue>
</port>
<port id="92" name="res_V_data_9_V" dir="1" iftype="3">
<core>FIFO</core><StgValue><ssdm name="res_V_data_9_V"/></StgValue>
</port>
</ports>


<dataflows>
<dataflow id="94" from="_ssdm_op_Read.ap_fifo.volatile.i16P.i16P.i16P.i16P.i16P.i16P.i16P.i16P.i16P.i16P" to="empty" fromId="93" toId="3">
</dataflow>
<dataflow id="95" from="data_V_data_0_V" to="empty" fromId="73" toId="3">
</dataflow>
<dataflow id="96" from="data_V_data_1_V" to="empty" fromId="74" toId="3">
</dataflow>
<dataflow id="97" from="data_V_data_2_V" to="empty" fromId="75" toId="3">
</dataflow>
<dataflow id="98" from="data_V_data_3_V" to="empty" fromId="76" toId="3">
</dataflow>
<dataflow id="99" from="data_V_data_4_V" to="empty" fromId="77" toId="3">
</dataflow>
<dataflow id="100" from="data_V_data_5_V" to="empty" fromId="78" toId="3">
</dataflow>
<dataflow id="101" from="data_V_data_6_V" to="empty" fromId="79" toId="3">
</dataflow>
<dataflow id="102" from="data_V_data_7_V" to="empty" fromId="80" toId="3">
</dataflow>
<dataflow id="103" from="data_V_data_8_V" to="empty" fromId="81" toId="3">
</dataflow>
<dataflow id="104" from="data_V_data_9_V" to="empty" fromId="82" toId="3">
</dataflow>
<dataflow id="105" from="empty" to="tmp_data_V_8_0" fromId="3" toId="4">
</dataflow>
<dataflow id="106" from="empty" to="tmp_data_V_8_1" fromId="3" toId="5">
</dataflow>
<dataflow id="107" from="empty" to="tmp_data_V_8_2" fromId="3" toId="6">
</dataflow>
<dataflow id="108" from="empty" to="tmp_data_V_8_3" fromId="3" toId="7">
</dataflow>
<dataflow id="109" from="empty" to="tmp_data_V_8_4" fromId="3" toId="8">
</dataflow>
<dataflow id="110" from="empty" to="tmp_data_V_8_5" fromId="3" toId="9">
</dataflow>
<dataflow id="111" from="empty" to="tmp_data_V_8_6" fromId="3" toId="10">
</dataflow>
<dataflow id="112" from="empty" to="tmp_data_V_8_7" fromId="3" toId="11">
</dataflow>
<dataflow id="113" from="empty" to="tmp_data_V_8_8" fromId="3" toId="12">
</dataflow>
<dataflow id="114" from="empty" to="tmp_data_V_8_9" fromId="3" toId="13">
</dataflow>
<dataflow id="115" from="tmp_data_V_8_0" to="icmp_ln1494" fromId="4" toId="14">
</dataflow>
<dataflow id="117" from="StgValue_116" to="icmp_ln1494" fromId="116" toId="14">
</dataflow>
<dataflow id="119" from="_ssdm_op_PartSelect.i8.i16.i32.i32" to="trunc_ln" fromId="118" toId="15">
</dataflow>
<dataflow id="120" from="tmp_data_V_8_0" to="trunc_ln" fromId="4" toId="15">
</dataflow>
<dataflow id="122" from="StgValue_121" to="trunc_ln" fromId="121" toId="15">
</dataflow>
<dataflow id="124" from="StgValue_123" to="trunc_ln" fromId="123" toId="15">
</dataflow>
<dataflow id="125" from="tmp_data_V_8_1" to="icmp_ln1494_1" fromId="5" toId="16">
</dataflow>
<dataflow id="126" from="StgValue_116" to="icmp_ln1494_1" fromId="116" toId="16">
</dataflow>
<dataflow id="127" from="_ssdm_op_PartSelect.i8.i16.i32.i32" to="trunc_ln708_1" fromId="118" toId="17">
</dataflow>
<dataflow id="128" from="tmp_data_V_8_1" to="trunc_ln708_1" fromId="5" toId="17">
</dataflow>
<dataflow id="129" from="StgValue_121" to="trunc_ln708_1" fromId="121" toId="17">
</dataflow>
<dataflow id="130" from="StgValue_123" to="trunc_ln708_1" fromId="123" toId="17">
</dataflow>
<dataflow id="131" from="tmp_data_V_8_2" to="icmp_ln1494_2" fromId="6" toId="18">
</dataflow>
<dataflow id="132" from="StgValue_116" to="icmp_ln1494_2" fromId="116" toId="18">
</dataflow>
<dataflow id="133" from="_ssdm_op_PartSelect.i8.i16.i32.i32" to="trunc_ln708_2" fromId="118" toId="19">
</dataflow>
<dataflow id="134" from="tmp_data_V_8_2" to="trunc_ln708_2" fromId="6" toId="19">
</dataflow>
<dataflow id="135" from="StgValue_121" to="trunc_ln708_2" fromId="121" toId="19">
</dataflow>
<dataflow id="136" from="StgValue_123" to="trunc_ln708_2" fromId="123" toId="19">
</dataflow>
<dataflow id="137" from="tmp_data_V_8_3" to="icmp_ln1494_3" fromId="7" toId="20">
</dataflow>
<dataflow id="138" from="StgValue_116" to="icmp_ln1494_3" fromId="116" toId="20">
</dataflow>
<dataflow id="139" from="_ssdm_op_PartSelect.i8.i16.i32.i32" to="trunc_ln708_3" fromId="118" toId="21">
</dataflow>
<dataflow id="140" from="tmp_data_V_8_3" to="trunc_ln708_3" fromId="7" toId="21">
</dataflow>
<dataflow id="141" from="StgValue_121" to="trunc_ln708_3" fromId="121" toId="21">
</dataflow>
<dataflow id="142" from="StgValue_123" to="trunc_ln708_3" fromId="123" toId="21">
</dataflow>
<dataflow id="143" from="tmp_data_V_8_4" to="icmp_ln1494_4" fromId="8" toId="22">
</dataflow>
<dataflow id="144" from="StgValue_116" to="icmp_ln1494_4" fromId="116" toId="22">
</dataflow>
<dataflow id="145" from="_ssdm_op_PartSelect.i8.i16.i32.i32" to="trunc_ln708_4" fromId="118" toId="23">
</dataflow>
<dataflow id="146" from="tmp_data_V_8_4" to="trunc_ln708_4" fromId="8" toId="23">
</dataflow>
<dataflow id="147" from="StgValue_121" to="trunc_ln708_4" fromId="121" toId="23">
</dataflow>
<dataflow id="148" from="StgValue_123" to="trunc_ln708_4" fromId="123" toId="23">
</dataflow>
<dataflow id="149" from="tmp_data_V_8_5" to="icmp_ln1494_5" fromId="9" toId="24">
</dataflow>
<dataflow id="150" from="StgValue_116" to="icmp_ln1494_5" fromId="116" toId="24">
</dataflow>
<dataflow id="151" from="_ssdm_op_PartSelect.i8.i16.i32.i32" to="trunc_ln708_5" fromId="118" toId="25">
</dataflow>
<dataflow id="152" from="tmp_data_V_8_5" to="trunc_ln708_5" fromId="9" toId="25">
</dataflow>
<dataflow id="153" from="StgValue_121" to="trunc_ln708_5" fromId="121" toId="25">
</dataflow>
<dataflow id="154" from="StgValue_123" to="trunc_ln708_5" fromId="123" toId="25">
</dataflow>
<dataflow id="155" from="tmp_data_V_8_6" to="icmp_ln1494_6" fromId="10" toId="26">
</dataflow>
<dataflow id="156" from="StgValue_116" to="icmp_ln1494_6" fromId="116" toId="26">
</dataflow>
<dataflow id="157" from="_ssdm_op_PartSelect.i8.i16.i32.i32" to="trunc_ln708_6" fromId="118" toId="27">
</dataflow>
<dataflow id="158" from="tmp_data_V_8_6" to="trunc_ln708_6" fromId="10" toId="27">
</dataflow>
<dataflow id="159" from="StgValue_121" to="trunc_ln708_6" fromId="121" toId="27">
</dataflow>
<dataflow id="160" from="StgValue_123" to="trunc_ln708_6" fromId="123" toId="27">
</dataflow>
<dataflow id="161" from="tmp_data_V_8_7" to="icmp_ln1494_7" fromId="11" toId="28">
</dataflow>
<dataflow id="162" from="StgValue_116" to="icmp_ln1494_7" fromId="116" toId="28">
</dataflow>
<dataflow id="163" from="_ssdm_op_PartSelect.i8.i16.i32.i32" to="trunc_ln708_7" fromId="118" toId="29">
</dataflow>
<dataflow id="164" from="tmp_data_V_8_7" to="trunc_ln708_7" fromId="11" toId="29">
</dataflow>
<dataflow id="165" from="StgValue_121" to="trunc_ln708_7" fromId="121" toId="29">
</dataflow>
<dataflow id="166" from="StgValue_123" to="trunc_ln708_7" fromId="123" toId="29">
</dataflow>
<dataflow id="167" from="tmp_data_V_8_8" to="icmp_ln1494_8" fromId="12" toId="30">
</dataflow>
<dataflow id="168" from="StgValue_116" to="icmp_ln1494_8" fromId="116" toId="30">
</dataflow>
<dataflow id="169" from="_ssdm_op_PartSelect.i8.i16.i32.i32" to="trunc_ln708_8" fromId="118" toId="31">
</dataflow>
<dataflow id="170" from="tmp_data_V_8_8" to="trunc_ln708_8" fromId="12" toId="31">
</dataflow>
<dataflow id="171" from="StgValue_121" to="trunc_ln708_8" fromId="121" toId="31">
</dataflow>
<dataflow id="172" from="StgValue_123" to="trunc_ln708_8" fromId="123" toId="31">
</dataflow>
<dataflow id="173" from="tmp_data_V_8_9" to="icmp_ln1494_9" fromId="13" toId="32">
</dataflow>
<dataflow id="174" from="StgValue_116" to="icmp_ln1494_9" fromId="116" toId="32">
</dataflow>
<dataflow id="175" from="_ssdm_op_PartSelect.i8.i16.i32.i32" to="trunc_ln708_9" fromId="118" toId="33">
</dataflow>
<dataflow id="176" from="tmp_data_V_8_9" to="trunc_ln708_9" fromId="13" toId="33">
</dataflow>
<dataflow id="177" from="StgValue_121" to="trunc_ln708_9" fromId="121" toId="33">
</dataflow>
<dataflow id="178" from="StgValue_123" to="trunc_ln708_9" fromId="123" toId="33">
</dataflow>
<dataflow id="179" from="icmp_ln1494" to="tmp_data_0_V" fromId="14" toId="34">
</dataflow>
<dataflow id="180" from="trunc_ln" to="tmp_data_0_V" fromId="15" toId="34">
</dataflow>
<dataflow id="182" from="StgValue_181" to="tmp_data_0_V" fromId="181" toId="34">
</dataflow>
<dataflow id="183" from="icmp_ln1494_1" to="tmp_data_1_V" fromId="16" toId="35">
</dataflow>
<dataflow id="184" from="trunc_ln708_1" to="tmp_data_1_V" fromId="17" toId="35">
</dataflow>
<dataflow id="185" from="StgValue_181" to="tmp_data_1_V" fromId="181" toId="35">
</dataflow>
<dataflow id="186" from="icmp_ln1494_2" to="tmp_data_2_V" fromId="18" toId="36">
</dataflow>
<dataflow id="187" from="trunc_ln708_2" to="tmp_data_2_V" fromId="19" toId="36">
</dataflow>
<dataflow id="188" from="StgValue_181" to="tmp_data_2_V" fromId="181" toId="36">
</dataflow>
<dataflow id="189" from="icmp_ln1494_3" to="tmp_data_3_V" fromId="20" toId="37">
</dataflow>
<dataflow id="190" from="trunc_ln708_3" to="tmp_data_3_V" fromId="21" toId="37">
</dataflow>
<dataflow id="191" from="StgValue_181" to="tmp_data_3_V" fromId="181" toId="37">
</dataflow>
<dataflow id="192" from="icmp_ln1494_4" to="tmp_data_4_V" fromId="22" toId="38">
</dataflow>
<dataflow id="193" from="trunc_ln708_4" to="tmp_data_4_V" fromId="23" toId="38">
</dataflow>
<dataflow id="194" from="StgValue_181" to="tmp_data_4_V" fromId="181" toId="38">
</dataflow>
<dataflow id="195" from="icmp_ln1494_5" to="tmp_data_5_V" fromId="24" toId="39">
</dataflow>
<dataflow id="196" from="trunc_ln708_5" to="tmp_data_5_V" fromId="25" toId="39">
</dataflow>
<dataflow id="197" from="StgValue_181" to="tmp_data_5_V" fromId="181" toId="39">
</dataflow>
<dataflow id="198" from="icmp_ln1494_6" to="tmp_data_6_V" fromId="26" toId="40">
</dataflow>
<dataflow id="199" from="trunc_ln708_6" to="tmp_data_6_V" fromId="27" toId="40">
</dataflow>
<dataflow id="200" from="StgValue_181" to="tmp_data_6_V" fromId="181" toId="40">
</dataflow>
<dataflow id="201" from="icmp_ln1494_7" to="tmp_data_7_V" fromId="28" toId="41">
</dataflow>
<dataflow id="202" from="trunc_ln708_7" to="tmp_data_7_V" fromId="29" toId="41">
</dataflow>
<dataflow id="203" from="StgValue_181" to="tmp_data_7_V" fromId="181" toId="41">
</dataflow>
<dataflow id="204" from="icmp_ln1494_8" to="tmp_data_8_V" fromId="30" toId="42">
</dataflow>
<dataflow id="205" from="trunc_ln708_8" to="tmp_data_8_V" fromId="31" toId="42">
</dataflow>
<dataflow id="206" from="StgValue_181" to="tmp_data_8_V" fromId="181" toId="42">
</dataflow>
<dataflow id="207" from="icmp_ln1494_9" to="tmp_data_9_V" fromId="32" toId="43">
</dataflow>
<dataflow id="208" from="trunc_ln708_9" to="tmp_data_9_V" fromId="33" toId="43">
</dataflow>
<dataflow id="209" from="StgValue_181" to="tmp_data_9_V" fromId="181" toId="43">
</dataflow>
<dataflow id="211" from="_ssdm_op_SpecInterface" to="specinterface_ln0" fromId="210" toId="44">
</dataflow>
<dataflow id="212" from="res_V_data_9_V" to="specinterface_ln0" fromId="92" toId="44">
</dataflow>
<dataflow id="214" from="ap_fifo_str" to="specinterface_ln0" fromId="213" toId="44">
</dataflow>
<dataflow id="216" from="StgValue_215" to="specinterface_ln0" fromId="215" toId="44">
</dataflow>
<dataflow id="217" from="StgValue_215" to="specinterface_ln0" fromId="215" toId="44">
</dataflow>
<dataflow id="219" from="p_str1693" to="specinterface_ln0" fromId="218" toId="44">
</dataflow>
<dataflow id="220" from="StgValue_215" to="specinterface_ln0" fromId="215" toId="44">
</dataflow>
<dataflow id="221" from="StgValue_215" to="specinterface_ln0" fromId="215" toId="44">
</dataflow>
<dataflow id="223" from="p_str1694" to="specinterface_ln0" fromId="222" toId="44">
</dataflow>
<dataflow id="225" from="p_str1695" to="specinterface_ln0" fromId="224" toId="44">
</dataflow>
<dataflow id="227" from="p_str1696" to="specinterface_ln0" fromId="226" toId="44">
</dataflow>
<dataflow id="229" from="StgValue_228" to="specinterface_ln0" fromId="228" toId="44">
</dataflow>
<dataflow id="230" from="StgValue_228" to="specinterface_ln0" fromId="228" toId="44">
</dataflow>
<dataflow id="232" from="StgValue_231" to="specinterface_ln0" fromId="231" toId="44">
</dataflow>
<dataflow id="233" from="StgValue_231" to="specinterface_ln0" fromId="231" toId="44">
</dataflow>
<dataflow id="235" from="p_str1697" to="specinterface_ln0" fromId="234" toId="44">
</dataflow>
<dataflow id="237" from="p_str1698" to="specinterface_ln0" fromId="236" toId="44">
</dataflow>
<dataflow id="238" from="_ssdm_op_SpecInterface" to="specinterface_ln0" fromId="210" toId="45">
</dataflow>
<dataflow id="239" from="res_V_data_8_V" to="specinterface_ln0" fromId="91" toId="45">
</dataflow>
<dataflow id="240" from="ap_fifo_str" to="specinterface_ln0" fromId="213" toId="45">
</dataflow>
<dataflow id="241" from="StgValue_215" to="specinterface_ln0" fromId="215" toId="45">
</dataflow>
<dataflow id="242" from="StgValue_215" to="specinterface_ln0" fromId="215" toId="45">
</dataflow>
<dataflow id="244" from="p_str1686" to="specinterface_ln0" fromId="243" toId="45">
</dataflow>
<dataflow id="245" from="StgValue_215" to="specinterface_ln0" fromId="215" toId="45">
</dataflow>
<dataflow id="246" from="StgValue_215" to="specinterface_ln0" fromId="215" toId="45">
</dataflow>
<dataflow id="248" from="p_str1687" to="specinterface_ln0" fromId="247" toId="45">
</dataflow>
<dataflow id="250" from="p_str1688" to="specinterface_ln0" fromId="249" toId="45">
</dataflow>
<dataflow id="252" from="p_str1689" to="specinterface_ln0" fromId="251" toId="45">
</dataflow>
<dataflow id="253" from="StgValue_228" to="specinterface_ln0" fromId="228" toId="45">
</dataflow>
<dataflow id="254" from="StgValue_228" to="specinterface_ln0" fromId="228" toId="45">
</dataflow>
<dataflow id="255" from="StgValue_231" to="specinterface_ln0" fromId="231" toId="45">
</dataflow>
<dataflow id="256" from="StgValue_231" to="specinterface_ln0" fromId="231" toId="45">
</dataflow>
<dataflow id="258" from="p_str1690" to="specinterface_ln0" fromId="257" toId="45">
</dataflow>
<dataflow id="260" from="p_str1691" to="specinterface_ln0" fromId="259" toId="45">
</dataflow>
<dataflow id="261" from="_ssdm_op_SpecInterface" to="specinterface_ln0" fromId="210" toId="46">
</dataflow>
<dataflow id="262" from="res_V_data_7_V" to="specinterface_ln0" fromId="90" toId="46">
</dataflow>
<dataflow id="263" from="ap_fifo_str" to="specinterface_ln0" fromId="213" toId="46">
</dataflow>
<dataflow id="264" from="StgValue_215" to="specinterface_ln0" fromId="215" toId="46">
</dataflow>
<dataflow id="265" from="StgValue_215" to="specinterface_ln0" fromId="215" toId="46">
</dataflow>
<dataflow id="267" from="p_str1679" to="specinterface_ln0" fromId="266" toId="46">
</dataflow>
<dataflow id="268" from="StgValue_215" to="specinterface_ln0" fromId="215" toId="46">
</dataflow>
<dataflow id="269" from="StgValue_215" to="specinterface_ln0" fromId="215" toId="46">
</dataflow>
<dataflow id="271" from="p_str1680" to="specinterface_ln0" fromId="270" toId="46">
</dataflow>
<dataflow id="273" from="p_str1681" to="specinterface_ln0" fromId="272" toId="46">
</dataflow>
<dataflow id="275" from="p_str1682" to="specinterface_ln0" fromId="274" toId="46">
</dataflow>
<dataflow id="276" from="StgValue_228" to="specinterface_ln0" fromId="228" toId="46">
</dataflow>
<dataflow id="277" from="StgValue_228" to="specinterface_ln0" fromId="228" toId="46">
</dataflow>
<dataflow id="278" from="StgValue_231" to="specinterface_ln0" fromId="231" toId="46">
</dataflow>
<dataflow id="279" from="StgValue_231" to="specinterface_ln0" fromId="231" toId="46">
</dataflow>
<dataflow id="281" from="p_str1683" to="specinterface_ln0" fromId="280" toId="46">
</dataflow>
<dataflow id="283" from="p_str1684" to="specinterface_ln0" fromId="282" toId="46">
</dataflow>
<dataflow id="284" from="_ssdm_op_SpecInterface" to="specinterface_ln0" fromId="210" toId="47">
</dataflow>
<dataflow id="285" from="res_V_data_6_V" to="specinterface_ln0" fromId="89" toId="47">
</dataflow>
<dataflow id="286" from="ap_fifo_str" to="specinterface_ln0" fromId="213" toId="47">
</dataflow>
<dataflow id="287" from="StgValue_215" to="specinterface_ln0" fromId="215" toId="47">
</dataflow>
<dataflow id="288" from="StgValue_215" to="specinterface_ln0" fromId="215" toId="47">
</dataflow>
<dataflow id="290" from="p_str1672" to="specinterface_ln0" fromId="289" toId="47">
</dataflow>
<dataflow id="291" from="StgValue_215" to="specinterface_ln0" fromId="215" toId="47">
</dataflow>
<dataflow id="292" from="StgValue_215" to="specinterface_ln0" fromId="215" toId="47">
</dataflow>
<dataflow id="294" from="p_str1673" to="specinterface_ln0" fromId="293" toId="47">
</dataflow>
<dataflow id="296" from="p_str1674" to="specinterface_ln0" fromId="295" toId="47">
</dataflow>
<dataflow id="298" from="p_str1675" to="specinterface_ln0" fromId="297" toId="47">
</dataflow>
<dataflow id="299" from="StgValue_228" to="specinterface_ln0" fromId="228" toId="47">
</dataflow>
<dataflow id="300" from="StgValue_228" to="specinterface_ln0" fromId="228" toId="47">
</dataflow>
<dataflow id="301" from="StgValue_231" to="specinterface_ln0" fromId="231" toId="47">
</dataflow>
<dataflow id="302" from="StgValue_231" to="specinterface_ln0" fromId="231" toId="47">
</dataflow>
<dataflow id="304" from="p_str1676" to="specinterface_ln0" fromId="303" toId="47">
</dataflow>
<dataflow id="306" from="p_str1677" to="specinterface_ln0" fromId="305" toId="47">
</dataflow>
<dataflow id="307" from="_ssdm_op_SpecInterface" to="specinterface_ln0" fromId="210" toId="48">
</dataflow>
<dataflow id="308" from="res_V_data_5_V" to="specinterface_ln0" fromId="88" toId="48">
</dataflow>
<dataflow id="309" from="ap_fifo_str" to="specinterface_ln0" fromId="213" toId="48">
</dataflow>
<dataflow id="310" from="StgValue_215" to="specinterface_ln0" fromId="215" toId="48">
</dataflow>
<dataflow id="311" from="StgValue_215" to="specinterface_ln0" fromId="215" toId="48">
</dataflow>
<dataflow id="313" from="p_str1665" to="specinterface_ln0" fromId="312" toId="48">
</dataflow>
<dataflow id="314" from="StgValue_215" to="specinterface_ln0" fromId="215" toId="48">
</dataflow>
<dataflow id="315" from="StgValue_215" to="specinterface_ln0" fromId="215" toId="48">
</dataflow>
<dataflow id="317" from="p_str1666" to="specinterface_ln0" fromId="316" toId="48">
</dataflow>
<dataflow id="319" from="p_str1667" to="specinterface_ln0" fromId="318" toId="48">
</dataflow>
<dataflow id="321" from="p_str1668" to="specinterface_ln0" fromId="320" toId="48">
</dataflow>
<dataflow id="322" from="StgValue_228" to="specinterface_ln0" fromId="228" toId="48">
</dataflow>
<dataflow id="323" from="StgValue_228" to="specinterface_ln0" fromId="228" toId="48">
</dataflow>
<dataflow id="324" from="StgValue_231" to="specinterface_ln0" fromId="231" toId="48">
</dataflow>
<dataflow id="325" from="StgValue_231" to="specinterface_ln0" fromId="231" toId="48">
</dataflow>
<dataflow id="327" from="p_str1669" to="specinterface_ln0" fromId="326" toId="48">
</dataflow>
<dataflow id="329" from="p_str1670" to="specinterface_ln0" fromId="328" toId="48">
</dataflow>
<dataflow id="330" from="_ssdm_op_SpecInterface" to="specinterface_ln0" fromId="210" toId="49">
</dataflow>
<dataflow id="331" from="res_V_data_4_V" to="specinterface_ln0" fromId="87" toId="49">
</dataflow>
<dataflow id="332" from="ap_fifo_str" to="specinterface_ln0" fromId="213" toId="49">
</dataflow>
<dataflow id="333" from="StgValue_215" to="specinterface_ln0" fromId="215" toId="49">
</dataflow>
<dataflow id="334" from="StgValue_215" to="specinterface_ln0" fromId="215" toId="49">
</dataflow>
<dataflow id="336" from="p_str1658" to="specinterface_ln0" fromId="335" toId="49">
</dataflow>
<dataflow id="337" from="StgValue_215" to="specinterface_ln0" fromId="215" toId="49">
</dataflow>
<dataflow id="338" from="StgValue_215" to="specinterface_ln0" fromId="215" toId="49">
</dataflow>
<dataflow id="340" from="p_str1659" to="specinterface_ln0" fromId="339" toId="49">
</dataflow>
<dataflow id="342" from="p_str1660" to="specinterface_ln0" fromId="341" toId="49">
</dataflow>
<dataflow id="344" from="p_str1661" to="specinterface_ln0" fromId="343" toId="49">
</dataflow>
<dataflow id="345" from="StgValue_228" to="specinterface_ln0" fromId="228" toId="49">
</dataflow>
<dataflow id="346" from="StgValue_228" to="specinterface_ln0" fromId="228" toId="49">
</dataflow>
<dataflow id="347" from="StgValue_231" to="specinterface_ln0" fromId="231" toId="49">
</dataflow>
<dataflow id="348" from="StgValue_231" to="specinterface_ln0" fromId="231" toId="49">
</dataflow>
<dataflow id="350" from="p_str1662" to="specinterface_ln0" fromId="349" toId="49">
</dataflow>
<dataflow id="352" from="p_str1663" to="specinterface_ln0" fromId="351" toId="49">
</dataflow>
<dataflow id="353" from="_ssdm_op_SpecInterface" to="specinterface_ln0" fromId="210" toId="50">
</dataflow>
<dataflow id="354" from="res_V_data_3_V" to="specinterface_ln0" fromId="86" toId="50">
</dataflow>
<dataflow id="355" from="ap_fifo_str" to="specinterface_ln0" fromId="213" toId="50">
</dataflow>
<dataflow id="356" from="StgValue_215" to="specinterface_ln0" fromId="215" toId="50">
</dataflow>
<dataflow id="357" from="StgValue_215" to="specinterface_ln0" fromId="215" toId="50">
</dataflow>
<dataflow id="359" from="p_str1651" to="specinterface_ln0" fromId="358" toId="50">
</dataflow>
<dataflow id="360" from="StgValue_215" to="specinterface_ln0" fromId="215" toId="50">
</dataflow>
<dataflow id="361" from="StgValue_215" to="specinterface_ln0" fromId="215" toId="50">
</dataflow>
<dataflow id="363" from="p_str1652" to="specinterface_ln0" fromId="362" toId="50">
</dataflow>
<dataflow id="365" from="p_str1653" to="specinterface_ln0" fromId="364" toId="50">
</dataflow>
<dataflow id="367" from="p_str1654" to="specinterface_ln0" fromId="366" toId="50">
</dataflow>
<dataflow id="368" from="StgValue_228" to="specinterface_ln0" fromId="228" toId="50">
</dataflow>
<dataflow id="369" from="StgValue_228" to="specinterface_ln0" fromId="228" toId="50">
</dataflow>
<dataflow id="370" from="StgValue_231" to="specinterface_ln0" fromId="231" toId="50">
</dataflow>
<dataflow id="371" from="StgValue_231" to="specinterface_ln0" fromId="231" toId="50">
</dataflow>
<dataflow id="373" from="p_str1655" to="specinterface_ln0" fromId="372" toId="50">
</dataflow>
<dataflow id="375" from="p_str1656" to="specinterface_ln0" fromId="374" toId="50">
</dataflow>
<dataflow id="376" from="_ssdm_op_SpecInterface" to="specinterface_ln0" fromId="210" toId="51">
</dataflow>
<dataflow id="377" from="res_V_data_2_V" to="specinterface_ln0" fromId="85" toId="51">
</dataflow>
<dataflow id="378" from="ap_fifo_str" to="specinterface_ln0" fromId="213" toId="51">
</dataflow>
<dataflow id="379" from="StgValue_215" to="specinterface_ln0" fromId="215" toId="51">
</dataflow>
<dataflow id="380" from="StgValue_215" to="specinterface_ln0" fromId="215" toId="51">
</dataflow>
<dataflow id="382" from="p_str1644" to="specinterface_ln0" fromId="381" toId="51">
</dataflow>
<dataflow id="383" from="StgValue_215" to="specinterface_ln0" fromId="215" toId="51">
</dataflow>
<dataflow id="384" from="StgValue_215" to="specinterface_ln0" fromId="215" toId="51">
</dataflow>
<dataflow id="386" from="p_str1645" to="specinterface_ln0" fromId="385" toId="51">
</dataflow>
<dataflow id="388" from="p_str1646" to="specinterface_ln0" fromId="387" toId="51">
</dataflow>
<dataflow id="390" from="p_str1647" to="specinterface_ln0" fromId="389" toId="51">
</dataflow>
<dataflow id="391" from="StgValue_228" to="specinterface_ln0" fromId="228" toId="51">
</dataflow>
<dataflow id="392" from="StgValue_228" to="specinterface_ln0" fromId="228" toId="51">
</dataflow>
<dataflow id="393" from="StgValue_231" to="specinterface_ln0" fromId="231" toId="51">
</dataflow>
<dataflow id="394" from="StgValue_231" to="specinterface_ln0" fromId="231" toId="51">
</dataflow>
<dataflow id="396" from="p_str1648" to="specinterface_ln0" fromId="395" toId="51">
</dataflow>
<dataflow id="398" from="p_str1649" to="specinterface_ln0" fromId="397" toId="51">
</dataflow>
<dataflow id="399" from="_ssdm_op_SpecInterface" to="specinterface_ln0" fromId="210" toId="52">
</dataflow>
<dataflow id="400" from="res_V_data_1_V" to="specinterface_ln0" fromId="84" toId="52">
</dataflow>
<dataflow id="401" from="ap_fifo_str" to="specinterface_ln0" fromId="213" toId="52">
</dataflow>
<dataflow id="402" from="StgValue_215" to="specinterface_ln0" fromId="215" toId="52">
</dataflow>
<dataflow id="403" from="StgValue_215" to="specinterface_ln0" fromId="215" toId="52">
</dataflow>
<dataflow id="405" from="p_str1637" to="specinterface_ln0" fromId="404" toId="52">
</dataflow>
<dataflow id="406" from="StgValue_215" to="specinterface_ln0" fromId="215" toId="52">
</dataflow>
<dataflow id="407" from="StgValue_215" to="specinterface_ln0" fromId="215" toId="52">
</dataflow>
<dataflow id="409" from="p_str1638" to="specinterface_ln0" fromId="408" toId="52">
</dataflow>
<dataflow id="411" from="p_str1639" to="specinterface_ln0" fromId="410" toId="52">
</dataflow>
<dataflow id="413" from="p_str1640" to="specinterface_ln0" fromId="412" toId="52">
</dataflow>
<dataflow id="414" from="StgValue_228" to="specinterface_ln0" fromId="228" toId="52">
</dataflow>
<dataflow id="415" from="StgValue_228" to="specinterface_ln0" fromId="228" toId="52">
</dataflow>
<dataflow id="416" from="StgValue_231" to="specinterface_ln0" fromId="231" toId="52">
</dataflow>
<dataflow id="417" from="StgValue_231" to="specinterface_ln0" fromId="231" toId="52">
</dataflow>
<dataflow id="419" from="p_str1641" to="specinterface_ln0" fromId="418" toId="52">
</dataflow>
<dataflow id="421" from="p_str1642" to="specinterface_ln0" fromId="420" toId="52">
</dataflow>
<dataflow id="422" from="_ssdm_op_SpecInterface" to="specinterface_ln0" fromId="210" toId="53">
</dataflow>
<dataflow id="423" from="res_V_data_0_V" to="specinterface_ln0" fromId="83" toId="53">
</dataflow>
<dataflow id="424" from="ap_fifo_str" to="specinterface_ln0" fromId="213" toId="53">
</dataflow>
<dataflow id="425" from="StgValue_215" to="specinterface_ln0" fromId="215" toId="53">
</dataflow>
<dataflow id="426" from="StgValue_215" to="specinterface_ln0" fromId="215" toId="53">
</dataflow>
<dataflow id="428" from="p_str1630" to="specinterface_ln0" fromId="427" toId="53">
</dataflow>
<dataflow id="429" from="StgValue_215" to="specinterface_ln0" fromId="215" toId="53">
</dataflow>
<dataflow id="430" from="StgValue_215" to="specinterface_ln0" fromId="215" toId="53">
</dataflow>
<dataflow id="432" from="p_str1631" to="specinterface_ln0" fromId="431" toId="53">
</dataflow>
<dataflow id="434" from="p_str1632" to="specinterface_ln0" fromId="433" toId="53">
</dataflow>
<dataflow id="436" from="p_str1633" to="specinterface_ln0" fromId="435" toId="53">
</dataflow>
<dataflow id="437" from="StgValue_228" to="specinterface_ln0" fromId="228" toId="53">
</dataflow>
<dataflow id="438" from="StgValue_228" to="specinterface_ln0" fromId="228" toId="53">
</dataflow>
<dataflow id="439" from="StgValue_231" to="specinterface_ln0" fromId="231" toId="53">
</dataflow>
<dataflow id="440" from="StgValue_231" to="specinterface_ln0" fromId="231" toId="53">
</dataflow>
<dataflow id="442" from="p_str1634" to="specinterface_ln0" fromId="441" toId="53">
</dataflow>
<dataflow id="444" from="p_str1635" to="specinterface_ln0" fromId="443" toId="53">
</dataflow>
<dataflow id="445" from="_ssdm_op_SpecInterface" to="specinterface_ln0" fromId="210" toId="54">
</dataflow>
<dataflow id="446" from="data_V_data_9_V" to="specinterface_ln0" fromId="82" toId="54">
</dataflow>
<dataflow id="447" from="ap_fifo_str" to="specinterface_ln0" fromId="213" toId="54">
</dataflow>
<dataflow id="448" from="StgValue_215" to="specinterface_ln0" fromId="215" toId="54">
</dataflow>
<dataflow id="449" from="StgValue_215" to="specinterface_ln0" fromId="215" toId="54">
</dataflow>
<dataflow id="451" from="p_str1623" to="specinterface_ln0" fromId="450" toId="54">
</dataflow>
<dataflow id="452" from="StgValue_215" to="specinterface_ln0" fromId="215" toId="54">
</dataflow>
<dataflow id="453" from="StgValue_215" to="specinterface_ln0" fromId="215" toId="54">
</dataflow>
<dataflow id="455" from="p_str1624" to="specinterface_ln0" fromId="454" toId="54">
</dataflow>
<dataflow id="457" from="p_str1625" to="specinterface_ln0" fromId="456" toId="54">
</dataflow>
<dataflow id="459" from="p_str1626" to="specinterface_ln0" fromId="458" toId="54">
</dataflow>
<dataflow id="460" from="StgValue_228" to="specinterface_ln0" fromId="228" toId="54">
</dataflow>
<dataflow id="461" from="StgValue_228" to="specinterface_ln0" fromId="228" toId="54">
</dataflow>
<dataflow id="462" from="StgValue_231" to="specinterface_ln0" fromId="231" toId="54">
</dataflow>
<dataflow id="463" from="StgValue_231" to="specinterface_ln0" fromId="231" toId="54">
</dataflow>
<dataflow id="465" from="p_str1627" to="specinterface_ln0" fromId="464" toId="54">
</dataflow>
<dataflow id="467" from="p_str1628" to="specinterface_ln0" fromId="466" toId="54">
</dataflow>
<dataflow id="468" from="_ssdm_op_SpecInterface" to="specinterface_ln0" fromId="210" toId="55">
</dataflow>
<dataflow id="469" from="data_V_data_8_V" to="specinterface_ln0" fromId="81" toId="55">
</dataflow>
<dataflow id="470" from="ap_fifo_str" to="specinterface_ln0" fromId="213" toId="55">
</dataflow>
<dataflow id="471" from="StgValue_215" to="specinterface_ln0" fromId="215" toId="55">
</dataflow>
<dataflow id="472" from="StgValue_215" to="specinterface_ln0" fromId="215" toId="55">
</dataflow>
<dataflow id="474" from="p_str1616" to="specinterface_ln0" fromId="473" toId="55">
</dataflow>
<dataflow id="475" from="StgValue_215" to="specinterface_ln0" fromId="215" toId="55">
</dataflow>
<dataflow id="476" from="StgValue_215" to="specinterface_ln0" fromId="215" toId="55">
</dataflow>
<dataflow id="478" from="p_str1617" to="specinterface_ln0" fromId="477" toId="55">
</dataflow>
<dataflow id="480" from="p_str1618" to="specinterface_ln0" fromId="479" toId="55">
</dataflow>
<dataflow id="482" from="p_str1619" to="specinterface_ln0" fromId="481" toId="55">
</dataflow>
<dataflow id="483" from="StgValue_228" to="specinterface_ln0" fromId="228" toId="55">
</dataflow>
<dataflow id="484" from="StgValue_228" to="specinterface_ln0" fromId="228" toId="55">
</dataflow>
<dataflow id="485" from="StgValue_231" to="specinterface_ln0" fromId="231" toId="55">
</dataflow>
<dataflow id="486" from="StgValue_231" to="specinterface_ln0" fromId="231" toId="55">
</dataflow>
<dataflow id="488" from="p_str1620" to="specinterface_ln0" fromId="487" toId="55">
</dataflow>
<dataflow id="490" from="p_str1621" to="specinterface_ln0" fromId="489" toId="55">
</dataflow>
<dataflow id="491" from="_ssdm_op_SpecInterface" to="specinterface_ln0" fromId="210" toId="56">
</dataflow>
<dataflow id="492" from="data_V_data_7_V" to="specinterface_ln0" fromId="80" toId="56">
</dataflow>
<dataflow id="493" from="ap_fifo_str" to="specinterface_ln0" fromId="213" toId="56">
</dataflow>
<dataflow id="494" from="StgValue_215" to="specinterface_ln0" fromId="215" toId="56">
</dataflow>
<dataflow id="495" from="StgValue_215" to="specinterface_ln0" fromId="215" toId="56">
</dataflow>
<dataflow id="497" from="p_str1609" to="specinterface_ln0" fromId="496" toId="56">
</dataflow>
<dataflow id="498" from="StgValue_215" to="specinterface_ln0" fromId="215" toId="56">
</dataflow>
<dataflow id="499" from="StgValue_215" to="specinterface_ln0" fromId="215" toId="56">
</dataflow>
<dataflow id="501" from="p_str1610" to="specinterface_ln0" fromId="500" toId="56">
</dataflow>
<dataflow id="503" from="p_str1611" to="specinterface_ln0" fromId="502" toId="56">
</dataflow>
<dataflow id="505" from="p_str1612" to="specinterface_ln0" fromId="504" toId="56">
</dataflow>
<dataflow id="506" from="StgValue_228" to="specinterface_ln0" fromId="228" toId="56">
</dataflow>
<dataflow id="507" from="StgValue_228" to="specinterface_ln0" fromId="228" toId="56">
</dataflow>
<dataflow id="508" from="StgValue_231" to="specinterface_ln0" fromId="231" toId="56">
</dataflow>
<dataflow id="509" from="StgValue_231" to="specinterface_ln0" fromId="231" toId="56">
</dataflow>
<dataflow id="511" from="p_str1613" to="specinterface_ln0" fromId="510" toId="56">
</dataflow>
<dataflow id="513" from="p_str1614" to="specinterface_ln0" fromId="512" toId="56">
</dataflow>
<dataflow id="514" from="_ssdm_op_SpecInterface" to="specinterface_ln0" fromId="210" toId="57">
</dataflow>
<dataflow id="515" from="data_V_data_6_V" to="specinterface_ln0" fromId="79" toId="57">
</dataflow>
<dataflow id="516" from="ap_fifo_str" to="specinterface_ln0" fromId="213" toId="57">
</dataflow>
<dataflow id="517" from="StgValue_215" to="specinterface_ln0" fromId="215" toId="57">
</dataflow>
<dataflow id="518" from="StgValue_215" to="specinterface_ln0" fromId="215" toId="57">
</dataflow>
<dataflow id="520" from="p_str1602" to="specinterface_ln0" fromId="519" toId="57">
</dataflow>
<dataflow id="521" from="StgValue_215" to="specinterface_ln0" fromId="215" toId="57">
</dataflow>
<dataflow id="522" from="StgValue_215" to="specinterface_ln0" fromId="215" toId="57">
</dataflow>
<dataflow id="524" from="p_str1603" to="specinterface_ln0" fromId="523" toId="57">
</dataflow>
<dataflow id="526" from="p_str1604" to="specinterface_ln0" fromId="525" toId="57">
</dataflow>
<dataflow id="528" from="p_str1605" to="specinterface_ln0" fromId="527" toId="57">
</dataflow>
<dataflow id="529" from="StgValue_228" to="specinterface_ln0" fromId="228" toId="57">
</dataflow>
<dataflow id="530" from="StgValue_228" to="specinterface_ln0" fromId="228" toId="57">
</dataflow>
<dataflow id="531" from="StgValue_231" to="specinterface_ln0" fromId="231" toId="57">
</dataflow>
<dataflow id="532" from="StgValue_231" to="specinterface_ln0" fromId="231" toId="57">
</dataflow>
<dataflow id="534" from="p_str1606" to="specinterface_ln0" fromId="533" toId="57">
</dataflow>
<dataflow id="536" from="p_str1607" to="specinterface_ln0" fromId="535" toId="57">
</dataflow>
<dataflow id="537" from="_ssdm_op_SpecInterface" to="specinterface_ln0" fromId="210" toId="58">
</dataflow>
<dataflow id="538" from="data_V_data_5_V" to="specinterface_ln0" fromId="78" toId="58">
</dataflow>
<dataflow id="539" from="ap_fifo_str" to="specinterface_ln0" fromId="213" toId="58">
</dataflow>
<dataflow id="540" from="StgValue_215" to="specinterface_ln0" fromId="215" toId="58">
</dataflow>
<dataflow id="541" from="StgValue_215" to="specinterface_ln0" fromId="215" toId="58">
</dataflow>
<dataflow id="543" from="p_str1595" to="specinterface_ln0" fromId="542" toId="58">
</dataflow>
<dataflow id="544" from="StgValue_215" to="specinterface_ln0" fromId="215" toId="58">
</dataflow>
<dataflow id="545" from="StgValue_215" to="specinterface_ln0" fromId="215" toId="58">
</dataflow>
<dataflow id="547" from="p_str1596" to="specinterface_ln0" fromId="546" toId="58">
</dataflow>
<dataflow id="549" from="p_str1597" to="specinterface_ln0" fromId="548" toId="58">
</dataflow>
<dataflow id="551" from="p_str1598" to="specinterface_ln0" fromId="550" toId="58">
</dataflow>
<dataflow id="552" from="StgValue_228" to="specinterface_ln0" fromId="228" toId="58">
</dataflow>
<dataflow id="553" from="StgValue_228" to="specinterface_ln0" fromId="228" toId="58">
</dataflow>
<dataflow id="554" from="StgValue_231" to="specinterface_ln0" fromId="231" toId="58">
</dataflow>
<dataflow id="555" from="StgValue_231" to="specinterface_ln0" fromId="231" toId="58">
</dataflow>
<dataflow id="557" from="p_str1599" to="specinterface_ln0" fromId="556" toId="58">
</dataflow>
<dataflow id="559" from="p_str1600" to="specinterface_ln0" fromId="558" toId="58">
</dataflow>
<dataflow id="560" from="_ssdm_op_SpecInterface" to="specinterface_ln0" fromId="210" toId="59">
</dataflow>
<dataflow id="561" from="data_V_data_4_V" to="specinterface_ln0" fromId="77" toId="59">
</dataflow>
<dataflow id="562" from="ap_fifo_str" to="specinterface_ln0" fromId="213" toId="59">
</dataflow>
<dataflow id="563" from="StgValue_215" to="specinterface_ln0" fromId="215" toId="59">
</dataflow>
<dataflow id="564" from="StgValue_215" to="specinterface_ln0" fromId="215" toId="59">
</dataflow>
<dataflow id="566" from="p_str1588" to="specinterface_ln0" fromId="565" toId="59">
</dataflow>
<dataflow id="567" from="StgValue_215" to="specinterface_ln0" fromId="215" toId="59">
</dataflow>
<dataflow id="568" from="StgValue_215" to="specinterface_ln0" fromId="215" toId="59">
</dataflow>
<dataflow id="570" from="p_str1589" to="specinterface_ln0" fromId="569" toId="59">
</dataflow>
<dataflow id="572" from="p_str1590" to="specinterface_ln0" fromId="571" toId="59">
</dataflow>
<dataflow id="574" from="p_str1591" to="specinterface_ln0" fromId="573" toId="59">
</dataflow>
<dataflow id="575" from="StgValue_228" to="specinterface_ln0" fromId="228" toId="59">
</dataflow>
<dataflow id="576" from="StgValue_228" to="specinterface_ln0" fromId="228" toId="59">
</dataflow>
<dataflow id="577" from="StgValue_231" to="specinterface_ln0" fromId="231" toId="59">
</dataflow>
<dataflow id="578" from="StgValue_231" to="specinterface_ln0" fromId="231" toId="59">
</dataflow>
<dataflow id="580" from="p_str1592" to="specinterface_ln0" fromId="579" toId="59">
</dataflow>
<dataflow id="582" from="p_str1593" to="specinterface_ln0" fromId="581" toId="59">
</dataflow>
<dataflow id="583" from="_ssdm_op_SpecInterface" to="specinterface_ln0" fromId="210" toId="60">
</dataflow>
<dataflow id="584" from="data_V_data_3_V" to="specinterface_ln0" fromId="76" toId="60">
</dataflow>
<dataflow id="585" from="ap_fifo_str" to="specinterface_ln0" fromId="213" toId="60">
</dataflow>
<dataflow id="586" from="StgValue_215" to="specinterface_ln0" fromId="215" toId="60">
</dataflow>
<dataflow id="587" from="StgValue_215" to="specinterface_ln0" fromId="215" toId="60">
</dataflow>
<dataflow id="589" from="p_str1581" to="specinterface_ln0" fromId="588" toId="60">
</dataflow>
<dataflow id="590" from="StgValue_215" to="specinterface_ln0" fromId="215" toId="60">
</dataflow>
<dataflow id="591" from="StgValue_215" to="specinterface_ln0" fromId="215" toId="60">
</dataflow>
<dataflow id="593" from="p_str1582" to="specinterface_ln0" fromId="592" toId="60">
</dataflow>
<dataflow id="595" from="p_str1583" to="specinterface_ln0" fromId="594" toId="60">
</dataflow>
<dataflow id="597" from="p_str1584" to="specinterface_ln0" fromId="596" toId="60">
</dataflow>
<dataflow id="598" from="StgValue_228" to="specinterface_ln0" fromId="228" toId="60">
</dataflow>
<dataflow id="599" from="StgValue_228" to="specinterface_ln0" fromId="228" toId="60">
</dataflow>
<dataflow id="600" from="StgValue_231" to="specinterface_ln0" fromId="231" toId="60">
</dataflow>
<dataflow id="601" from="StgValue_231" to="specinterface_ln0" fromId="231" toId="60">
</dataflow>
<dataflow id="603" from="p_str1585" to="specinterface_ln0" fromId="602" toId="60">
</dataflow>
<dataflow id="605" from="p_str1586" to="specinterface_ln0" fromId="604" toId="60">
</dataflow>
<dataflow id="606" from="_ssdm_op_SpecInterface" to="specinterface_ln0" fromId="210" toId="61">
</dataflow>
<dataflow id="607" from="data_V_data_2_V" to="specinterface_ln0" fromId="75" toId="61">
</dataflow>
<dataflow id="608" from="ap_fifo_str" to="specinterface_ln0" fromId="213" toId="61">
</dataflow>
<dataflow id="609" from="StgValue_215" to="specinterface_ln0" fromId="215" toId="61">
</dataflow>
<dataflow id="610" from="StgValue_215" to="specinterface_ln0" fromId="215" toId="61">
</dataflow>
<dataflow id="612" from="p_str1574" to="specinterface_ln0" fromId="611" toId="61">
</dataflow>
<dataflow id="613" from="StgValue_215" to="specinterface_ln0" fromId="215" toId="61">
</dataflow>
<dataflow id="614" from="StgValue_215" to="specinterface_ln0" fromId="215" toId="61">
</dataflow>
<dataflow id="616" from="p_str1575" to="specinterface_ln0" fromId="615" toId="61">
</dataflow>
<dataflow id="618" from="p_str1576" to="specinterface_ln0" fromId="617" toId="61">
</dataflow>
<dataflow id="620" from="p_str1577" to="specinterface_ln0" fromId="619" toId="61">
</dataflow>
<dataflow id="621" from="StgValue_228" to="specinterface_ln0" fromId="228" toId="61">
</dataflow>
<dataflow id="622" from="StgValue_228" to="specinterface_ln0" fromId="228" toId="61">
</dataflow>
<dataflow id="623" from="StgValue_231" to="specinterface_ln0" fromId="231" toId="61">
</dataflow>
<dataflow id="624" from="StgValue_231" to="specinterface_ln0" fromId="231" toId="61">
</dataflow>
<dataflow id="626" from="p_str1578" to="specinterface_ln0" fromId="625" toId="61">
</dataflow>
<dataflow id="628" from="p_str1579" to="specinterface_ln0" fromId="627" toId="61">
</dataflow>
<dataflow id="629" from="_ssdm_op_SpecInterface" to="specinterface_ln0" fromId="210" toId="62">
</dataflow>
<dataflow id="630" from="data_V_data_1_V" to="specinterface_ln0" fromId="74" toId="62">
</dataflow>
<dataflow id="631" from="ap_fifo_str" to="specinterface_ln0" fromId="213" toId="62">
</dataflow>
<dataflow id="632" from="StgValue_215" to="specinterface_ln0" fromId="215" toId="62">
</dataflow>
<dataflow id="633" from="StgValue_215" to="specinterface_ln0" fromId="215" toId="62">
</dataflow>
<dataflow id="635" from="p_str1567" to="specinterface_ln0" fromId="634" toId="62">
</dataflow>
<dataflow id="636" from="StgValue_215" to="specinterface_ln0" fromId="215" toId="62">
</dataflow>
<dataflow id="637" from="StgValue_215" to="specinterface_ln0" fromId="215" toId="62">
</dataflow>
<dataflow id="639" from="p_str1568" to="specinterface_ln0" fromId="638" toId="62">
</dataflow>
<dataflow id="641" from="p_str1569" to="specinterface_ln0" fromId="640" toId="62">
</dataflow>
<dataflow id="643" from="p_str1570" to="specinterface_ln0" fromId="642" toId="62">
</dataflow>
<dataflow id="644" from="StgValue_228" to="specinterface_ln0" fromId="228" toId="62">
</dataflow>
<dataflow id="645" from="StgValue_228" to="specinterface_ln0" fromId="228" toId="62">
</dataflow>
<dataflow id="646" from="StgValue_231" to="specinterface_ln0" fromId="231" toId="62">
</dataflow>
<dataflow id="647" from="StgValue_231" to="specinterface_ln0" fromId="231" toId="62">
</dataflow>
<dataflow id="649" from="p_str1571" to="specinterface_ln0" fromId="648" toId="62">
</dataflow>
<dataflow id="651" from="p_str1572" to="specinterface_ln0" fromId="650" toId="62">
</dataflow>
<dataflow id="652" from="_ssdm_op_SpecInterface" to="specinterface_ln0" fromId="210" toId="63">
</dataflow>
<dataflow id="653" from="data_V_data_0_V" to="specinterface_ln0" fromId="73" toId="63">
</dataflow>
<dataflow id="654" from="ap_fifo_str" to="specinterface_ln0" fromId="213" toId="63">
</dataflow>
<dataflow id="655" from="StgValue_215" to="specinterface_ln0" fromId="215" toId="63">
</dataflow>
<dataflow id="656" from="StgValue_215" to="specinterface_ln0" fromId="215" toId="63">
</dataflow>
<dataflow id="658" from="p_str1560" to="specinterface_ln0" fromId="657" toId="63">
</dataflow>
<dataflow id="659" from="StgValue_215" to="specinterface_ln0" fromId="215" toId="63">
</dataflow>
<dataflow id="660" from="StgValue_215" to="specinterface_ln0" fromId="215" toId="63">
</dataflow>
<dataflow id="662" from="p_str1561" to="specinterface_ln0" fromId="661" toId="63">
</dataflow>
<dataflow id="664" from="p_str1562" to="specinterface_ln0" fromId="663" toId="63">
</dataflow>
<dataflow id="666" from="p_str1563" to="specinterface_ln0" fromId="665" toId="63">
</dataflow>
<dataflow id="667" from="StgValue_228" to="specinterface_ln0" fromId="228" toId="63">
</dataflow>
<dataflow id="668" from="StgValue_228" to="specinterface_ln0" fromId="228" toId="63">
</dataflow>
<dataflow id="669" from="StgValue_231" to="specinterface_ln0" fromId="231" toId="63">
</dataflow>
<dataflow id="670" from="StgValue_231" to="specinterface_ln0" fromId="231" toId="63">
</dataflow>
<dataflow id="672" from="p_str1564" to="specinterface_ln0" fromId="671" toId="63">
</dataflow>
<dataflow id="674" from="p_str1565" to="specinterface_ln0" fromId="673" toId="63">
</dataflow>
<dataflow id="676" from="_ssdm_op_SpecLoopName" to="specloopname_ln41" fromId="675" toId="64">
</dataflow>
<dataflow id="678" from="p_str56" to="specloopname_ln41" fromId="677" toId="64">
</dataflow>
<dataflow id="680" from="_ssdm_op_SpecRegionBegin" to="tmp" fromId="679" toId="65">
</dataflow>
<dataflow id="681" from="p_str56" to="tmp" fromId="677" toId="65">
</dataflow>
<dataflow id="683" from="_ssdm_op_SpecPipeline" to="specpipeline_ln42" fromId="682" toId="66">
</dataflow>
<dataflow id="685" from="StgValue_684" to="specpipeline_ln42" fromId="684" toId="66">
</dataflow>
<dataflow id="687" from="StgValue_686" to="specpipeline_ln42" fromId="686" toId="66">
</dataflow>
<dataflow id="688" from="StgValue_686" to="specpipeline_ln42" fromId="686" toId="66">
</dataflow>
<dataflow id="689" from="StgValue_215" to="specpipeline_ln42" fromId="215" toId="66">
</dataflow>
<dataflow id="691" from="p_str17" to="specpipeline_ln42" fromId="690" toId="66">
</dataflow>
<dataflow id="693" from="_ssdm_op_Write.ap_fifo.volatile.i8P.i8P.i8P.i8P.i8P.i8P.i8P.i8P.i8P.i8P" to="write_ln57" fromId="692" toId="67">
</dataflow>
<dataflow id="694" from="res_V_data_0_V" to="write_ln57" fromId="83" toId="67">
</dataflow>
<dataflow id="695" from="res_V_data_1_V" to="write_ln57" fromId="84" toId="67">
</dataflow>
<dataflow id="696" from="res_V_data_2_V" to="write_ln57" fromId="85" toId="67">
</dataflow>
<dataflow id="697" from="res_V_data_3_V" to="write_ln57" fromId="86" toId="67">
</dataflow>
<dataflow id="698" from="res_V_data_4_V" to="write_ln57" fromId="87" toId="67">
</dataflow>
<dataflow id="699" from="res_V_data_5_V" to="write_ln57" fromId="88" toId="67">
</dataflow>
<dataflow id="700" from="res_V_data_6_V" to="write_ln57" fromId="89" toId="67">
</dataflow>
<dataflow id="701" from="res_V_data_7_V" to="write_ln57" fromId="90" toId="67">
</dataflow>
<dataflow id="702" from="res_V_data_8_V" to="write_ln57" fromId="91" toId="67">
</dataflow>
<dataflow id="703" from="res_V_data_9_V" to="write_ln57" fromId="92" toId="67">
</dataflow>
<dataflow id="704" from="tmp_data_0_V" to="write_ln57" fromId="34" toId="67">
</dataflow>
<dataflow id="705" from="tmp_data_1_V" to="write_ln57" fromId="35" toId="67">
</dataflow>
<dataflow id="706" from="tmp_data_2_V" to="write_ln57" fromId="36" toId="67">
</dataflow>
<dataflow id="707" from="tmp_data_3_V" to="write_ln57" fromId="37" toId="67">
</dataflow>
<dataflow id="708" from="tmp_data_4_V" to="write_ln57" fromId="38" toId="67">
</dataflow>
<dataflow id="709" from="tmp_data_5_V" to="write_ln57" fromId="39" toId="67">
</dataflow>
<dataflow id="710" from="tmp_data_6_V" to="write_ln57" fromId="40" toId="67">
</dataflow>
<dataflow id="711" from="tmp_data_7_V" to="write_ln57" fromId="41" toId="67">
</dataflow>
<dataflow id="712" from="tmp_data_8_V" to="write_ln57" fromId="42" toId="67">
</dataflow>
<dataflow id="713" from="tmp_data_9_V" to="write_ln57" fromId="43" toId="67">
</dataflow>
<dataflow id="715" from="_ssdm_op_SpecRegionEnd" to="empty_34" fromId="714" toId="68">
</dataflow>
<dataflow id="716" from="p_str56" to="empty_34" fromId="677" toId="68">
</dataflow>
<dataflow id="717" from="tmp" to="empty_34" fromId="65" toId="68">
</dataflow>
</dataflows>


</stg>
